lvl_3/lvl3_lab01.sv
/* verilator lint_off DECLFILENAME */
module logic_unit #(
/* verilator lint_on DECLFILENAME */
    parameter WIDTH = 16
) (
    input wire [WIDTH-1:0] in_a,
    input wire [WIDTH-1:0] in_b,
    input wire [3:0]       select,
    output wire [WIDTH-1:0] logic_out
    
);

    logic [WIDTH-1:0] res;

    always_comb begin
        case (select)
            4'h0: res = ~in_a;
            4'h1: res = ~(in_a | in_b); 
            4'h2: res = ~in_a & in_b; 
            4'h3: res = 16'h0; 
            4'h4: res = ~(in_a & in_b); 
            4'h5: res = ~in_b; 
            4'h6: res = in_a ^ in_b; 
            4'h7: res = in_a & ~in_b; 
            4'h8: res = ~in_a | in_b; 
            4'h9: res = ~(in_a ^ in_b); 
            4'hA: res = in_b; 
            4'hB: res = in_a & in_b; 
            4'hC: res = 16'h1; 
            4'hD: res = in_a | ~in_b; 
            4'hE: res = in_a | in_b; 
            4'hF: res = in_a; 
            default: res = 16'h0;
        endcase
    end
    /*
    0000 0000 0000 1000
    0000 0000 0000 1001
    
    0000 0000 0000 1001
    */

    assign logic_out = res;

endmodule

module arithmetic #(
    parameter WIDTH = 16
) (
    input wire carry_in,
    input wire [WIDTH-1:0] in_a,
    input wire [WIDTH-1:0] in_b,
    input wire [3:0]       select,
    output wire cmp,
    output wire carry_out,
    output wire [WIDTH-1:0] arithmetic_out
);

    logic [WIDTH:0] extended_res;
    assign carry_out = 0;

    
                /*
                0000 0000 0000 1010
                0000 0000 0000 1001

                01111 1111 1111 0110
            or  00000 0000 0000 1010
                01111 1111 1111 1110

                */

    always_comb begin
        case (select)
            4'h0: extended_res = {1'b0, in_a}; // Extend in_a to 17 bits
            4'h1: extended_res = {1'b0, in_a} | {1'b0, in_b}; // Extend both to 17 bits
            4'h2: extended_res = {1'b0, in_a} | {1'b0, ~in_b}; // Extend both to 17 bits
            4'h3: extended_res = ~{{WIDTH{1'b0}}, 1'b1} + 1; // 17-bit zero
            4'h4: extended_res = {1'b0, in_a} | ({1'b0, in_a} & {1'b0, ~in_b}); // Extend all to 17 bits
            4'h5: extended_res = {1'b0, (in_a | in_b) + (in_a & ~in_b)} + {{WIDTH{1'b0}}, carry_in};
            4'h6: extended_res = {1'b0, in_a} + {1'b0, ~in_b}; // Extend both to 17 bits
            4'h7: extended_res = {1'b0, in_a & ~in_b}; // Extend to 17 bits
            4'h8: extended_res = {1'b0, in_a} + {1'b0, in_a & in_b} + {{WIDTH{1'b0}}, carry_in}; // Extend to 17 bits
            4'h9: extended_res = {1'b0, in_a} + {1'b0, in_b} + {{WIDTH{1'b0}}, carry_in}; // Extend to 17 bits
            4'hA: extended_res = {1'b0, in_a | ~in_b} + {1'b0, in_a & in_b} + {{WIDTH{1'b0}}, carry_in}; // Extend to 17 bits
            4'hB: extended_res = {1'b0, in_a & in_b}; // Extend to 17 bits
            4'hC: extended_res = {1'b0, in_a} + {1'b0, in_a} + {{WIDTH{1'b0}}, carry_in}; // Extend to 17 bits
            4'hD: extended_res = {1'b0, in_a | in_b} + {1'b0, in_a} + {{WIDTH{1'b0}}, carry_in}; // Extend to 17 bits
            4'hE: extended_res = {1'b0, in_a | ~in_b} + {1'b0, in_a} + {{WIDTH{1'b0}}, carry_in}; // Extend to 17 bits
            4'hF: extended_res = {1'b0, in_a} + {{WIDTH{1'b0}}, carry_in}; // Extend to 17 bits
            default: extended_res = {WIDTH+1{1'b0}}; // 17-bit zero
        endcase
    end
    /*
    
    0000 0000 0000 0001

    1111 1111 1111 1110
    0000 0000 0000 0011
    1111 1111 1111 1111

    0001
    0111
    
    1000
    0001

    1001
    0001
    1010
    */

    assign arithmetic_out = extended_res[WIDTH-1:0];
    assign carry_out = extended_res[WIDTH];
    assign cmp = (in_a == in_b) ? 1 : 0;

endmodule

module alu #(
    parameter WIDTH = 16
) (
    //input clk,
    //input rst,

    //input  operation_t  op_in, //instead of select ig -> could it be used?
    input  wire         carry_in,
    input  wire [WIDTH-1:0]  a_in,
    input  wire [WIDTH-1:0]  b_in,
    input  wire [3:0]        select,
    input  wire              mode,
    
    output wire              carry_out,
    output wire              compare,
    output wire [WIDTH-1:0]  alu_out
);

    logic [WIDTH-1:0] res;
    logic [WIDTH-1:0] logic_res;
    logic [WIDTH-1:0] arithmetic_res;
    logic car_out, car_arith;
    logic cmp, cmp_ari;

    logic_unit u1 (
        .in_a(a_in),
        .in_b(b_in),
        .select(select),
        .logic_out(logic_res)
    );

    arithmetic u2 (
        .in_a(a_in),
        .in_b(b_in),
        .select(select),
        .carry_in(carry_in),
        .arithmetic_out(arithmetic_res),
        .cmp(cmp_ari),
        .carry_out(car_arith)
    );
    always begin
        if(a_in == b_in) begin
            cmp = 1;
        end
        else begin
            cmp = 0;
        end
    end


    always_comb begin
        if(mode == 1) begin
            res = logic_res;
            car_out = 0;
        end else begin
            res = arithmetic_res;
            cmp = cmp_ari;
            car_out = car_arith;
        end
    end

    assign carry_out = car_out;
    assign alu_out = res;
    assign compare = cmp;

endmodule

lvl_3/waveform.vcd
$version Generated by VerilatedVcd $end
$date Mon Jun  3 19:33:21 2024
 $end
$timescale   1ns $end

 $scope module TOP $end
  $var wire 16 [ a_in [15:0] $end
  $var wire 16 -! alu_out [15:0] $end
  $var wire 16 c b_in [15:0] $end
  $var wire  1 S carry_in $end
  $var wire  1 { carry_out $end
  $var wire  1 %! compare $end
  $var wire  1 s mode $end
  $var wire  4 k select [3:0] $end
  $scope module alu $end
   $var wire 32 E! WIDTH [31:0] $end
   $var wire 16 [ a_in [15:0] $end
   $var wire 16 -! alu_out [15:0] $end
   $var wire 16 + arithmetic_res [15:0] $end
   $var wire 16 c b_in [15:0] $end
   $var wire  1 ; car_arith $end
   $var wire  1 3 car_out $end
   $var wire  1 S carry_in $end
   $var wire  1 { carry_out $end
   $var wire  1 C cmp $end
   $var wire  1 =! cmp_ari $end
   $var wire  1 %! compare $end
   $var wire 16 # logic_res [15:0] $end
   $var wire  1 s mode $end
   $var wire 16 5! res [15:0] $end
   $var wire  4 k select [3:0] $end
   $scope module u1 $end
    $var wire 32 E! WIDTH [31:0] $end
    $var wire 16 [ in_a [15:0] $end
    $var wire 16 c in_b [15:0] $end
    $var wire 16 # logic_out [15:0] $end
    $var wire 16 # res [15:0] $end
    $var wire  4 k select [3:0] $end
   $upscope $end
   $scope module u2 $end
    $var wire 32 E! WIDTH [31:0] $end
    $var wire 16 + arithmetic_out [15:0] $end
    $var wire  1 S carry_in $end
    $var wire  1 ; carry_out $end
    $var wire  1 =! cmp $end
    $var wire 17 K extended_res [16:0] $end
    $var wire 16 [ in_a [15:0] $end
    $var wire 16 c in_b [15:0] $end
    $var wire  4 k select [3:0] $end
   $upscope $end
  $upscope $end
 $upscope $end
$enddefinitions $end


#0
b0100111100100000 #
b1011000011011111 +
03
0;
0C
b01011000011011111 K
1S
b1011000001011001 [
b0011000011011110 c
b0001 k
1s
0{
0%!
b0100111100100000 -!
b0100111100100000 5!
0=!
b00000000000000000000000000010000 E!
#1
#2
#3
#4
#5
#6
#7
#8
#9
#10
b0000000000000110 [
b0000000000000010 c
b1110 k
#11
b0000000000000110 #
b0000000000000110 +
1;
b10000000000000110 K
0S
b0000000000001001 [
b0000000000001010 c
b1111 k
b0000000000000110 -!
b0000000000000110 5!
#12
b0000000000001001 #
b0000000000001001 +
0;
b00000000000001001 K
b0000000000001001 -!
b0000000000001001 5!
#13
#14
#15
#16
#17
#18
#19
#20
#21
#22
#23
#24
#25
#26
1S
b0000000000000110 [
b0000000000001000 c
b0110 k
#27
b0000000000001110 #
b1111111111111101 +
b01111111111111101 K
b0000000000001110 -!
b0000000000001110 5!
#28
#29
#30
#31
b0000000000000100 [
b0000000000000111 c
b1010 k
0s
b1111111111111101 5!
#32
b0000000000000111 #
b0000000000000001 +
13
1;
b10000000000000001 K
1{
b0000000000000001 -!
b0000000000000001 5!
#33
#34
#35
#36
#37
0S
b0000000000000011 [
b0000000000000100 c
b0010 k
#38
b0000000000000100 #
b1111111111111011 +
03
0;
b01111111111111011 K
1S
b0000000000001010 [
b0000000000000000 c
b1000 k
1s
0{
b1111111111111011 -!
b0000000000000100 5!
#39
b1111111111110101 #
b0000000000001011 +
b00000000000001011 K
0S
b0000000000000101 [
b0001 k
b1111111111110101 -!
b1111111111110101 5!
#40
b1111111111111010 #
b0000000000000101 +
b00000000000000101 K
b1111111111111010 -!
b1111111111111010 5!
#41
#42
1S
b0000000000000111 [
b0000000000000011 c
b0101 k
#43
b1111111111111100 #
b0000000000001100 +
b00000000000001100 K
b0000000000000000 [
b0000000000000000 c
b0111 k
0s
b1111111111111100 -!
b0000000000001100 5!
1=!
#44
b0000000000000000 #
b0000000000000000 +
1C
b00000000000000000 K
1%!
b0000000000000000 -!
b0000000000000000 5!
#45
#46
#47
#48
b0000000000000111 [
b0000000000001001 c
b1010 k
0=!
#49
b0000000000001001 #
b1111111111111001 +
0C
b01111111111111001 K
0%!
b1111111111111001 -!
b1111111111111001 5!
#50
0S
b0000000000000110 [
b0000000000001010 c
b1000 k
1s
b0000000000001001 5!
#51
b1111111111111011 #
b0000000000001000 +
b00000000000001000 K
b1111111111111011 -!
b1111111111111011 5!
#52
#53
#54
#55
b0000000000000101 [
b0000000000000110 c
0s
b0000000000001000 5!
#56
b1111111111111110 #
b0000000000001001 +
b00000000000001001 K
b0000000000001001 -!
b0000000000001001 5!
#57
1S
b0000000000000110 [
b0000000000000011 c
b0101 k
#58
b1111111111111100 #
b0000000000001100 +
b00000000000001100 K
b0000000000001100 -!
b0000000000001100 5!
#59
#60
0S
b0000000000001001 c
b1010 k
#61
b0000000000001001 #
b1111111111110110 +
b01111111111110110 K
b1111111111110110 -!
b1111111111110110 5!
#62
1S
b0000000000000101 [
b0000000000000011 c
1s
b0000000000001001 5!
#63
b0000000000000011 #
b1111111111111111 +
b01111111111111111 K
0S
b0000000000000100 [
b0000000000000010 c
b1001 k
0s
b0000000000000011 -!
b1111111111111111 5!
#64
b1111111111111001 #
b0000000000000110 +
b00000000000000110 K
b0000000000000110 -!
b0000000000000110 5!
#65
#66
#67
#68
#69
#70
1S
b0000000000000101 [
b0000000000001000 c
b0000 k
#71
b1111111111111010 #
b0000000000000101 +
b00000000000000101 K
b0000000000001010 c
b1011 k
1s
b0000000000000101 -!
b1111111111111010 5!
#72
b0000000000000000 #
b0000000000000000 +
b00000000000000000 K
b0000000000000000 -!
b0000000000000000 5!
#73
0S
b0000000000001010 [
b0000000000000100 c
b0000 k
0s
#74
b1111111111110101 #
b0000000000001010 +
b00000000000001010 K
b0000000000000000 c
b1100 k
b0000000000001010 -!
b0000000000001010 5!
#75
b0000000000000001 #
b0000000000010100 +
b00000000000010100 K
b0000000000010100 -!
b0000000000010100 5!
#76
b0000000000000000 [
b0000000000001000 c
b1010 k
#77
b0000000000001000 #
b1111111111110111 +
b01111111111110111 K
1S
b0000000000000100 [
b0000000000000111 c
b1101 k
1s
b1111111111110111 -!
b0000000000001000 5!
#78
b1111111111111100 #
b0000000000001100 +
b00000000000001100 K
b1111111111111100 -!
b1111111111111100 5!
#79
#80
#81
b0000000000001001 [
b0000000000000010 c
b0100 k
0s
b0000000000001100 5!
#82
b1111111111111111 #
b0000000000001001 +
b00000000000001001 K
b0000000000001001 -!
b0000000000001001 5!
#83
#84
#85
b0000000000000001 [
b0000000000000001 c
1=!
#86
b1111111111111110 #
b0000000000000001 +
1C
b00000000000000001 K
1%!
b0000000000000001 -!
b0000000000000001 5!
#87
#88
#89
0S
b0000000000001001 [
b0000000000000011 c
1s
b1111111111111110 5!
0=!
#90
b0000000000001001 +
0C
b00000000000001001 K
1S
b0000000000001000 [
b0000000000000001 c
b1011 k
0s
0%!
b1111111111111110 -!
b0000000000001001 5!
#91
b0000000000000000 #
b0000000000000000 +
b00000000000000000 K
b0000000000000000 -!
b0000000000000000 5!
#92
#93
#94
#95
b0000000000000110 [
b0000000000000100 c
#96
b0000000000000100 #
b0000000000000100 +
b00000000000000100 K
b0000000000000100 -!
b0000000000000100 5!
#97
0S
b0000000000000111 [
b0000000000001000 c
b0101 k
1s
#98
b1111111111110111 #
b0000000000010110 +
b00000000000010110 K
b1111111111110111 -!
b1111111111110111 5!
#99
b0000000000000110 [
b0100 k
#100
b1111111111111111 #
b0000000000000110 +
b00000000000000110 K
b1111111111111111 -!
b1111111111111111 5!
#101
#102
#103
#104
#105
#106
b0000000000001000 [
b0000000000000000 c
b1000 k
#107
b1111111111110111 #
b0000000000001000 +
b00000000000001000 K
b1111111111110111 -!
b1111111111110111 5!
#108
#109
#110
#111
#112
#113
#114
#115
#116
b0000000000000010 [
b0000000000001001 c
0s
b0000000000001000 5!
#117
b1111111111111101 #
b0000000000000010 +
b00000000000000010 K
b0000000000000010 -!
b0000000000000010 5!
#118
1S
b0000000000000011 [
b0000000000001010 c
b1111 k
#119
b0000000000000011 #
b0000000000000100 +
b00000000000000100 K
0S
b0000000000001010 [
b0000000000000011 c
b0010 k
b0000000000000100 -!
b0000000000000100 5!
#120
b0000000000000001 #
b1111111111111110 +
b01111111111111110 K
b1111111111111110 -!
b1111111111111110 5!
#121
#122
#123
#124
#125
#126
#127
#128
#129
#130
1S
b0000000000000101 [
b0000000000000111 c
b0101 k
1s
b0000000000000001 5!
#131
b1111111111111000 #
b0000000000001000 +
b00000000000001000 K
b1111111111111000 -!
b1111111111111000 5!
#132
#133
#134
#135
#136
b0000000000000011 [
b1011 k
0s
b0000000000001000 5!
#137
b0000000000000011 #
b0000000000000011 +
b00000000000000011 K
b0000000000000111 [
b0000000000001010 c
b1100 k
1s
b0000000000000011 -!
b0000000000000011 5!
#138
b0000000000000001 #
b0000000000001111 +
b00000000000001111 K
b0000000000000001 -!
b0000000000000001 5!
#139
#140
#141
#142
#143
#144
0S
b0000000000000010 [
b0000000000000101 c
b0100 k
#145
b1111111111111111 #
b0000000000000010 +
b00000000000000010 K
b1111111111111111 -!
b1111111111111111 5!
#146
1S
b0000000000000011 [
b0000000000000001 c
b1111 k
0s
b0000000000000010 5!
#147
b0000000000000011 #
b0000000000000100 +
b00000000000000100 K
b0000000000000100 -!
b0000000000000100 5!
#148
#149
#150
#151
b0000000000001010 [
b0000000000000111 c
b0111 k
1s
b0000000000000011 5!
#152
b0000000000001000 #
b0000000000001000 +
b00000000000001000 K
b0000000000001000 -!
b0000000000001000 5!
#153
#154
#155
b0000000000000011 [
b0000000000001000 c
b1010 k
#156
b1111111111111000 +
b01111111111111000 K
0S
b0000000000000110 [
b0000000000000011 c
b0111 k
#157
b0000000000000100 #
b0000000000000100 +
b00000000000000100 K
b0000000000000100 -!
b0000000000000100 5!
#158
#159
#160
#161
#162
#163
#164
#165
1S
b0000000000001000 [
b1000 k
0s
#166
b1111111111110111 #
b0000000000001001 +
b00000000000001001 K
b0000000000001001 -!
b0000000000001001 5!
#167
#168
#169
#170
#171
#172
#173
b0000000000000010 [
b0000000000001000 c
b0100 k
#174
b1111111111111111 #
b0000000000000010 +
b00000000000000010 K
0S
b0000000000000000 [
b0000000000001010 c
b0010 k
b0000000000000010 -!
b0000000000000010 5!
#175
b0000000000001010 #
b1111111111110101 +
b01111111111110101 K
b1111111111110101 -!
b1111111111110101 5!
#176
#177
#178
b0000000000001001 [
b0000000000000001 c
b1010 k
#179
b0000000000000001 #
b0000000000000000 +
13
1;
b10000000000000000 K
1{
b0000000000000000 -!
b0000000000000000 5!
#180
#181
#182
#183
#184
#185
#186
#187
#188
#189
#190
#191
1S
b0000000000001000 [
b0000000000001001 c
b0001 k
1s
b0000000000000001 5!
#192
b1111111111110110 #
b0000000000001001 +
03
0;
b00000000000001001 K
0{
b1111111111110110 -!
b1111111111110110 5!
#193
#194
#195
#196
#197
#198
#199
#200
#201
#202
#203
#204
b0000000000000100 [
b0000000000000010 c
b1010 k
#205
b0000000000000010 #
b1111111111111110 +
b01111111111111110 K
b0000000000000010 -!
b0000000000000010 5!
#206
b0000000000000000 [
b0000000000000001 c
b1000 k
#207
b1111111111111111 #
b0000000000000001 +
b00000000000000001 K
b1111111111111111 -!
b1111111111111111 5!
#208
#209
b0000000000001001 [
b0000000000001000 c
b1010 k
0s
b0000000000000001 5!
#210
b0000000000001000 #
b0000000000001000 +
13
1;
b10000000000001000 K
0S
b0000000000001010 [
b0000000000000100 c
b0101 k
1s
1{
b0000000000001000 -!
b0000000000001000 5!
#211
b1111111111111011 #
b0000000000011000 +
03
0;
b00000000000011000 K
0{
b1111111111111011 -!
b1111111111111011 5!
#212
1S
b0000000000000110 [
b0000000000001010 c
b0111 k
#213
b0000000000000100 #
b0000000000000100 +
b00000000000000100 K
b0000000000000100 -!
b0000000000000100 5!
#214
#215
b0000000000000111 [
b0000000000001000 c
#216
b0000000000000111 #
b0000000000000111 +
b00000000000000111 K
b0000000000000100 [
b0000000000000110 c
b1000 k
b0000000000000111 -!
b0000000000000111 5!
#217
b1111111111111111 #
b0000000000001001 +
b00000000000001001 K
b1111111111111111 -!
b1111111111111111 5!
#218
#219
#220
0S
b0000000000000110 [
b0000000000001001 c
b1111 k
0s
b0000000000001001 5!
#221
b0000000000000110 #
b0000000000000110 +
b00000000000000110 K
b0000000000000110 -!
b0000000000000110 5!
#222
#223
#224
#225
#226
#227
#228
b0000000000000001 [
b0000000000000111 c
b1101 k
#229
b1111111111111001 #
b0000000000001000 +
b00000000000001000 K
b0000000000001000 -!
b0000000000001000 5!
#230
#231
#232
#233
#234
#235
#236
#237
#238
1S
b0000000000000000 [
b0000000000000011 c
b0100 k
#239
b1111111111111111 #
b0000000000000000 +
b00000000000000000 K
b0000000000000000 -!
b0000000000000000 5!
#240
#241
#242
b0000000000000100 [
b0000000000000001 c
b1110 k
#243
b0000000000000101 #
b0000000000000011 +
13
1;
b10000000000000011 K
1{
b0000000000000011 -!
b0000000000000011 5!
#244
#245
#246
b0000000000000111 [
b0000000000001001 c
b0010 k
#247
b0000000000001000 #
b1111111111110111 +
03
0;
b01111111111110111 K
0{
b1111111111110111 -!
b1111111111110111 5!
#248
#249
#250
#251
#252
#253
#254
#255
b0000000000000001 [
b0000000000001000 c
b0110 k
1s
b0000000000001000 5!
#256
b0000000000001001 #
b1111111111111000 +
b01111111111111000 K
b0000000000001001 -!
b0000000000001001 5!
#257
0S
b0000000000000111 [
b0000000000000010 c
0s
b1111111111111000 5!
#258
b0000000000000101 #
b0000000000000100 +
13
1;
b10000000000000100 K
1{
b0000000000000100 -!
b0000000000000100 5!
#259
1S
b0000000000000001 [
b0000000000001001 c
b1010 k
1s
b0000000000000101 5!
#260
b0000000000001001 #
b1111111111111001 +
03
0;
b01111111111111001 K
0{
b0000000000001001 -!
b0000000000001001 5!
#261
#262
#263
b0000000000001010 [
b0000000000000100 c
b1011 k
#264
b0000000000000000 #
b0000000000000000 +
b00000000000000000 K
b0000000000000000 -!
b0000000000000000 5!
#265
#266
#267
#268
0S
b0000000000000010 [
b0000000000000011 c
b1000 k
#269
b1111111111111111 #
b0000000000000100 +
b00000000000000100 K
b1111111111111111 -!
b1111111111111111 5!
#270
#271
b0000000000000101 [
b0000000000001001 c
b0010 k
0s
b0000000000000100 5!
#272
b0000000000001000 #
b1111111111110111 +
b01111111111110111 K
b0000000000001001 [
b0000000000000101 c
b1101 k
1s
b1111111111110111 -!
b0000000000001000 5!
#273
b1111111111111011 #
b0000000000010110 +
b00000000000010110 K
b1111111111111011 -!
b1111111111111011 5!
#274
1S
b0000000000001000 [
b0000000000001001 c
b1111 k
0s
b0000000000010110 5!
#275
b0000000000001000 #
b0000000000001001 +
b00000000000001001 K
b0000000000001001 -!
b0000000000001001 5!
#276
b0000000000001010 [
b0000000000000111 c
b0111 k
#277
b0000000000001000 +
b00000000000001000 K
b0000000000001000 -!
b0000000000001000 5!
#278
#279
0S
b0000000000000111 [
b0000000000000101 c
b0000 k
#280
b1111111111111000 #
b0000000000000111 +
b00000000000000111 K
b0000000000000111 -!
b0000000000000111 5!
#281
#282
b0000000000000110 [
b0000000000001010 c
b0111 k
1s
b1111111111111000 5!
#283
b0000000000000100 #
b0000000000000100 +
b00000000000000100 K
b0000000000000100 -!
b0000000000000100 5!
#284
#285
b0000000000000101 [
b0000000000000001 c
b0010 k
0s
#286
b0000000000000000 #
b1111111111111111 +
b01111111111111111 K
b1111111111111111 -!
b1111111111111111 5!
#287
#288
#289
1S
b0000000000000000 [
b0000000000000100 c
b0101 k
#290
b1111111111111011 #
b0000000000000101 +
b00000000000000101 K
b0000000000000101 -!
b0000000000000101 5!
#291
b0000000000000111 c
b0010 k
#292
b0000000000000111 #
b1111111111111000 +
b01111111111111000 K
b1111111111111000 -!
b1111111111111000 5!
#293
#294
#295
#296
b0000000000000111 [
b0000000000000100 c
b0000 k
1s
b0000000000000111 5!
#297
b1111111111111000 #
b0000000000000111 +
b00000000000000111 K
b1111111111111000 5!
