lvl_3/lvl3_lab01.sv
/* verilator lint_off DECLFILENAME */
module logic_unit #(
/* verilator lint_on DECLFILENAME */
    parameter WIDTH = 16
) (
    input wire [WIDTH-1:0] in_a,
    input wire [WIDTH-1:0] in_b,
    input wire [3:0]       select,
    output wire [WIDTH-1:0] logic_out
    
);

    logic [WIDTH-1:0] res;

    always_comb begin
        case (select)
            4'h0: res = ~in_a;
            4'h1: res = ~(in_a | in_b); 
            4'h2: res = ~in_a & in_b; 
            4'h3: res = 16'h0; 
            4'h4: res = ~(in_a & in_b); 
            4'h5: res = ~in_b; 
            4'h6: res = in_a ^ in_b; 
            4'h7: res = in_a & ~in_b; 
            4'h8: res = ~in_a | in_b; 
            4'h9: res = ~(in_a ^ in_b); 
            4'hA: res = in_b; 
            4'hB: res = in_a & in_b; 
            4'hC: res = 16'h1; 
            4'hD: res = in_a | ~in_b; 
            4'hE: res = in_a | in_b; 
            4'hF: res = in_a; 
            default: res = 16'h0;
        endcase
    end
    /*
    0000 0000 0000 1000
    0000 0000 0000 1001
    
    0000 0000 0000 1001
    */

    assign logic_out = res;

endmodule

module arithmetic #(
    parameter WIDTH = 16
) (
    input wire carry_in,
    input wire [WIDTH-1:0] in_a,
    input wire [WIDTH-1:0] in_b,
    input wire [3:0]       select,
    output wire cmp,
    output wire carry_out,
    output wire [WIDTH-1:0] arithmetic_out
);

    logic [WIDTH:0] extended_res;
    assign carry_out = 0;

    
                /*
                0000 0000 0000 1010
                0000 0000 0000 1001

                01111 1111 1111 0110
            or  00000 0000 0000 1010
                01111 1111 1111 1110

                */

    always_comb begin
        case (select)
            4'h0: extended_res = {1'b0, in_a}; // Extend in_a to 17 bits
            4'h1: extended_res = {1'b0, in_a} | {1'b0, in_b}; // Extend both to 17 bits
            4'h2: extended_res = {1'b0, in_a} | {1'b0, ~in_b}; // Extend both to 17 bits
            4'h3: extended_res = ~{{WIDTH{1'b0}}, 1'b1} + 1; // 17-bit zero
            4'h4: extended_res = {1'b0, in_a} | ({1'b0, in_a} & {1'b0, ~in_b}); // Extend all to 17 bits
            4'h5: extended_res = {1'b0, (in_a | in_b) + (in_a & ~in_b)} + {{WIDTH{1'b0}}, carry_in};
            4'h6: extended_res = {1'b0, in_a} + {1'b0, ~in_b}; // Extend both to 17 bits
            4'h7: extended_res = {1'b0, in_a & ~in_b}; // Extend to 17 bits
            4'h8: extended_res = {1'b0, in_a} + {1'b0, in_a & in_b} + {{WIDTH{1'b0}}, carry_in}; // Extend to 17 bits
            4'h9: extended_res = {1'b0, in_a} + {1'b0, in_b} + {{WIDTH{1'b0}}, carry_in}; // Extend to 17 bits
            4'hA: extended_res = {1'b0, in_a | ~in_b} + {1'b0, in_a & in_b} + {{WIDTH{1'b0}}, carry_in}; // Extend to 17 bits
            4'hB: extended_res = {1'b0, in_a & in_b}; // Extend to 17 bits
            4'hC: extended_res = {1'b0, in_a} + {1'b0, in_a} + {{WIDTH{1'b0}}, carry_in}; // Extend to 17 bits
            4'hD: extended_res = {1'b0, in_a | in_b} + {1'b0, in_a} + {{WIDTH{1'b0}}, carry_in}; // Extend to 17 bits
            4'hE: extended_res = {1'b0, in_a | ~in_b} + {1'b0, in_a} + {{WIDTH{1'b0}}, carry_in}; // Extend to 17 bits
            4'hF: extended_res = {1'b0, in_a} + {{WIDTH{1'b0}}, carry_in}; // Extend to 17 bits
            default: extended_res = {WIDTH+1{1'b0}}; // 17-bit zero
        endcase
    end
    /*
    
    0000 0000 0000 0001

    1111 1111 1111 1110
    0000 0000 0000 0011
    1111 1111 1111 1111

    0001
    0111
    
    1000
    0001

    1001
    0001
    1010
    */

    assign arithmetic_out = extended_res[WIDTH-1:0];
    assign carry_out = extended_res[WIDTH];
    assign cmp = (in_a == in_b) ? 1 : 0;

endmodule

module alu #(
    parameter WIDTH = 16
) (
    //input clk,
    //input rst,

    //input  operation_t  op_in, //instead of select ig -> could it be used?
    input  wire         carry_in,
    input  wire [WIDTH-1:0]  a_in,
    input  wire [WIDTH-1:0]  b_in,
    input  wire [3:0]        select,
    input  wire              mode,
    
    output wire              carry_out,
    output wire              compare,
    output wire [WIDTH-1:0]  alu_out
);

    logic [WIDTH-1:0] res;
    logic [WIDTH-1:0] logic_res;
    logic [WIDTH-1:0] arithmetic_res;
    logic car_out, car_arith;
    logic cmp, cmp_ari;

    logic_unit u1 (
        .in_a(a_in),
        .in_b(b_in),
        .select(select),
        .logic_out(logic_res)
    );

    arithmetic u2 (
        .in_a(a_in),
        .in_b(b_in),
        .select(select),
        .carry_in(carry_in),
        .arithmetic_out(arithmetic_res),
        .cmp(cmp_ari),
        .carry_out(car_arith)
    );
    always begin
        if(a_in == b_in) begin
            cmp = 1;
        end
        else begin
            cmp = 0;
        end
    end


    always_comb begin
        if(mode == 1) begin
            res = logic_res;
            car_out = 0;
        end else begin
            res = arithmetic_res;
            cmp = cmp_ari;
            car_out = car_arith;
        end
    end

    assign carry_out = car_out;
    assign alu_out = res;
    assign compare = cmp;

endmodule

lvl_3/waveform.vcd
$version Generated by VerilatedVcd $end
$date Wed Jun 19 13:12:49 2024
 $end
$timescale   1ns $end

 $scope module TOP $end
  $var wire 16 [ a_in [15:0] $end
  $var wire 16 -! alu_out [15:0] $end
  $var wire 16 c b_in [15:0] $end
  $var wire  1 S carry_in $end
  $var wire  1 { carry_out $end
  $var wire  1 %! compare $end
  $var wire  1 s mode $end
  $var wire  4 k select [3:0] $end
  $scope module alu $end
   $var wire 32 E! WIDTH [31:0] $end
   $var wire 16 [ a_in [15:0] $end
   $var wire 16 -! alu_out [15:0] $end
   $var wire 16 + arithmetic_res [15:0] $end
   $var wire 16 c b_in [15:0] $end
   $var wire  1 ; car_arith $end
   $var wire  1 3 car_out $end
   $var wire  1 S carry_in $end
   $var wire  1 { carry_out $end
   $var wire  1 C cmp $end
   $var wire  1 =! cmp_ari $end
   $var wire  1 %! compare $end
   $var wire 16 # logic_res [15:0] $end
   $var wire  1 s mode $end
   $var wire 16 5! res [15:0] $end
   $var wire  4 k select [3:0] $end
   $scope module u1 $end
    $var wire 32 E! WIDTH [31:0] $end
    $var wire 16 [ in_a [15:0] $end
    $var wire 16 c in_b [15:0] $end
    $var wire 16 # logic_out [15:0] $end
    $var wire 16 # res [15:0] $end
    $var wire  4 k select [3:0] $end
   $upscope $end
   $scope module u2 $end
    $var wire 32 E! WIDTH [31:0] $end
    $var wire 16 + arithmetic_out [15:0] $end
    $var wire  1 S carry_in $end
    $var wire  1 ; carry_out $end
    $var wire  1 =! cmp $end
    $var wire 17 K extended_res [16:0] $end
    $var wire 16 [ in_a [15:0] $end
    $var wire 16 c in_b [15:0] $end
    $var wire  4 k select [3:0] $end
   $upscope $end
  $upscope $end
 $upscope $end
$enddefinitions $end


#0
b0100111100100000 #
b1011000011011111 +
03
0;
0C
b01011000011011111 K
1S
b1011000001011001 [
b0011000011011110 c
b0001 k
1s
0{
0%!
b0100111100100000 -!
b0100111100100000 5!
0=!
b00000000000000000000000000010000 E!
#1
#2
#3
#4
#5
#6
#7
#8
0S
b0000000000001001 [
b0000000000000110 c
b1000 k
#9
b1111111111110110 #
b0000000000001001 +
b00000000000001001 K
b0000000000000010 c
b0001 k
b1111111111110110 -!
b1111111111110110 5!
#10
b1111111111110100 #
b0000000000001011 +
b00000000000001011 K
b1111111111110100 -!
b1111111111110100 5!
#11
b0000000000000010 [
b0000000000001010 c
b1001 k
#12
b1111111111110111 #
b0000000000001100 +
b00000000000001100 K
b1111111111110111 -!
b1111111111110111 5!
#13
#14
#15
1S
b0000000000001010 [
b0000000000000001 c
b0001 k
0s
b0000000000001100 5!
#16
b1111111111110100 #
b0000000000001011 +
b00000000000001011 K
0S
b0000000000001000 [
b0000000000001000 c
b1100 k
b0000000000001011 -!
b0000000000001011 5!
1=!
#17
b0000000000000001 #
b0000000000010000 +
1C
b00000000000010000 K
b0000000000000100 [
b0000000000000111 c
b0101 k
1%!
b0000000000010000 -!
b0000000000010000 5!
0=!
#18
b1111111111111000 #
b0000000000000111 +
0C
b00000000000000111 K
0%!
b0000000000000111 -!
b0000000000000111 5!
#19
#20
1S
b0000000000000000 [
b0000000000000100 c
b1001 k
1s
b1111111111111000 5!
#21
b1111111111111011 #
b0000000000000101 +
b00000000000000101 K
b1111111111111011 -!
b1111111111111011 5!
#22
#23
#24
#25
#26
#27
#28
#29
#30
b0000000000000000 c
b0000 k
0s
b0000000000000101 5!
1=!
#31
b1111111111111111 #
b0000000000000000 +
1C
b00000000000000000 K
1%!
b0000000000000000 -!
b0000000000000000 5!
#32
#33
#34
#35
#36
#37
#38
#39
#40
#41
#42
#43
#44
#45
#46
#47
#48
#49
0S
b0000000000000010 [
b0000000000001001 c
b1010 k
1s
b1111111111111111 5!
0=!
#50
b0000000000001001 #
b1111111111110110 +
0C
b01111111111110110 K
0%!
b0000000000001001 -!
b0000000000001001 5!
#51
#52
#53
#54
#55
#56
#57
b0000000000000001 [
b0000000000001000 c
b1111 k
#58
b0000000000000001 #
b0000000000000001 +
b00000000000000001 K
b0000000000000001 -!
b0000000000000001 5!
#59
#60
#61
#62
#63
1S
b0000000000000110 [
b0000000000000100 c
b1100 k
#64
b0000000000001101 +
b00000000000001101 K
#65
#66
#67
#68
#69
b0000000000001010 c
b0111 k
#70
b0000000000000100 #
b0000000000000100 +
b00000000000000100 K
b0000000000000100 -!
b0000000000000100 5!
#71
#72
#73
#74
#75
#76
#77
#78
#79
#80
0S
b0000000000001010 [
b0000000000000100 c
b1011 k
0s
#81
b0000000000000000 #
b0000000000000000 +
b00000000000000000 K
b0000000000000000 -!
b0000000000000000 5!
#82
b0000000000000100 [
b0000000000000001 c
b1101 k
1s
#83
b1111111111111110 #
b0000000000001001 +
b00000000000001001 K
b1111111111111110 -!
b1111111111111110 5!
#84
#85
#86
1S
b0000000000001001 [
b0000000000001010 c
b1110 k
0s
b0000000000001001 5!
#87
b0000000000001011 #
b0000000000000111 +
13
1;
b10000000000000111 K
1{
b0000000000000111 -!
b0000000000000111 5!
#88
#89
0S
b0000000000000100 [
b0000000000000111 c
b0101 k
#90
b1111111111111000 #
03
0;
b00000000000000111 K
0{
#91
#92
#93
#94
b0000000000001000 c
b0110 k
1s
b1111111111111000 5!
#95
b0000000000001100 #
b1111111111111011 +
b01111111111111011 K
1S
b0000000000000110 [
b0000000000000001 c
b0001 k
b0000000000001100 -!
b0000000000001100 5!
#96
b1111111111111000 #
b0000000000000111 +
b00000000000000111 K
b1111111111111000 -!
b1111111111111000 5!
#97
#98
#99
#100
#101
#102
#103
#104
#105
#106
#107
#108
#109
#110
#111
#112
#113
#114
0S
b0000000000000111 [
b0000000000000010 c
b1010 k
0s
b0000000000000111 5!
#115
b0000000000000010 #
b0000000000000001 +
13
1;
b10000000000000001 K
1{
b0000000000000001 -!
b0000000000000001 5!
#116
#117
1S
b0000000000000011 [
b0000000000000001 c
b1100 k
1s
b0000000000000010 5!
#118
b0000000000000001 #
b0000000000000111 +
03
0;
b00000000000000111 K
0{
b0000000000000001 5!
#119
0S
b0000000000001000 [
b0000000000000011 c
b1000 k
0s
b0000000000000111 5!
#120
b1111111111110111 #
b0000000000001000 +
b00000000000001000 K
b0000000000001000 -!
b0000000000001000 5!
#121
#122
#123
#124
#125
#126
b0000000000000010 [
b0000000000001010 c
b1010 k
#127
b0000000000001010 #
b1111111111111001 +
b01111111111111001 K
b1111111111111001 -!
b1111111111111001 5!
#128
#129
#130
#131
#132
#133
#134
#135
#136
#137
1S
b0000000000000110 [
b0000000000000000 c
b1001 k
1s
b0000000000001010 5!
#138
b1111111111111001 #
b0000000000000111 +
b00000000000000111 K
b1111111111111001 5!
#139
#140
b0000000000000000 [
b0000000000001010 c
b0010 k
0s
b0000000000000111 5!
#141
b0000000000001010 #
b1111111111110101 +
b01111111111110101 K
b1111111111110101 -!
b1111111111110101 5!
#142
#143
#144
0S
b0000000000001010 [
b0000000000001001 c
b1101 k
#145
b1111111111111110 #
b0000000000010101 +
b00000000000010101 K
b0000000000010101 -!
b0000000000010101 5!
#146
#147
#148
#149
#150
1S
b0000000000000001 [
b0000000000000110 c
b0000 k
#151
b0000000000000001 +
b00000000000000001 K
b0000000000000001 -!
b0000000000000001 5!
#152
b0000000000000101 [
b0000000000000111 c
b1000 k
1s
b1111111111111110 5!
#153
b1111111111111111 #
b0000000000001011 +
b00000000000001011 K
b1111111111111111 -!
b1111111111111111 5!
#154
#155
b0000000000001000 [
b0000000000000011 c
b1100 k
0s
b0000000000001011 5!
#156
b0000000000000001 #
b0000000000010001 +
b00000000000010001 K
b0000000000001001 [
b0000000000001000 c
b0010 k
1s
b0000000000010001 -!
b0000000000000001 5!
#157
b0000000000000000 #
b1111111111111111 +
b01111111111111111 K
b0000000000000000 -!
b0000000000000000 5!
#158
#159
#160
#161
0S
b0000000000001000 [
b0000000000000101 c
b1010 k
0s
b1111111111111111 5!
#162
b0000000000000101 #
b1111111111111010 +
b01111111111111010 K
1S
b0000000000000011 c
b1111 k
b1111111111111010 -!
b1111111111111010 5!
#163
b0000000000001000 #
b0000000000001001 +
b00000000000001001 K
b0000000000001001 -!
b0000000000001001 5!
#164
0S
b0000000000000110 [
b0000000000000010 c
b0001 k
1s
b0000000000001000 5!
#165
b1111111111111001 #
b0000000000000110 +
b00000000000000110 K
b1111111111111001 -!
b1111111111111001 5!
#166
b0000000000001001 [
b0000000000000100 c
b0110 k
#167
b0000000000001101 #
b0000000000000100 +
1;
b10000000000000100 K
b0000000000001101 -!
b0000000000001101 5!
#168
#169
#170
#171
1S
b0000000000000111 [
b0000000000000000 c
b1100 k
#172
b0000000000000001 #
b0000000000001111 +
0;
b00000000000001111 K
b0000000000000001 -!
b0000000000000001 5!
#173
#174
#175
#176
#177
#178
#179
#180
#181
#182
#183
#184
0S
b0000000000000110 [
b0000000000001001 c
b1001 k
#185
b1111111111110000 #
b1111111111110000 -!
b1111111111110000 5!
#186
#187
#188
#189
#190
1S
b0000000000000101 [
b0000000000000000 c
0s
b0000000000001111 5!
#191
b1111111111111010 #
b0000000000000110 +
b00000000000000110 K
b0000000000000010 c
b1000 k
1s
b0000000000000110 -!
b1111111111111010 5!
#192
0S
b0000000000001000 [
b0000000000000100 c
b1111 k
0s
b1111111111111010 -!
b0000000000000110 5!
#193
b0000000000001000 #
b0000000000001000 +
b00000000000001000 K
b0000000000001000 -!
b0000000000001000 5!
#194
b0000000000000000 c
b1110 k
#195
b0000000000000111 +
13
1;
b10000000000000111 K
1{
b0000000000000111 -!
b0000000000000111 5!
#196
#197
#198
#199
#200
#201
#202
#203
b0000000000000010 [
b0000000000001000 c
1s
b0000000000001000 5!
#204
b0000000000001010 #
b1111111111111001 +
03
0;
b01111111111111001 K
0{
b0000000000001010 -!
b0000000000001010 5!
#205
#206
#207
1S
b0000000000000000 [
b0000000000001001 c
b1100 k
0s
b1111111111111001 5!
#208
b0000000000000001 #
b0000000000000001 +
b00000000000000001 K
b0000000000000001 -!
b0000000000000001 5!
#209
#210
#211
#212
#213
#214
0S
b0000000000000101 [
b0000000000000010 c
#215
b0000000000001010 +
b00000000000001010 K
b0000000000001010 -!
b0000000000001010 5!
#216
#217
#218
1S
b0000000000000001 [
b0000000000000100 c
b1111 k
1s
b0000000000000001 5!
#219
b0000000000000010 +
b00000000000000010 K
b0000000000000001 -!
#220
#221
#222
#223
#224
0S
b0000000000000010 [
b0000000000000011 c
b0110 k
#225
b1111111111111110 +
b01111111111111110 K
#226
#227
#228
#229
#230
#231
#232
#233
#234
#235
#236
#237
#238
#239
#240
#241
#242
#243
1S
b0000000000000000 [
b0000000000001010 c
b0101 k
#244
b1111111111110101 #
b0000000000001011 +
b00000000000001011 K
b1111111111110101 -!
b1111111111110101 5!
#245
b0000000000000010 [
b0000000000000001 c
#246
b1111111111111110 #
b0000000000000110 +
b00000000000000110 K
b1111111111111110 -!
b1111111111111110 5!
#247
0S
b0000000000000100 [
b0000000000000101 c
b1100 k
0s
b0000000000000110 5!
#248
b0000000000000001 #
b0000000000001000 +
b00000000000001000 K
b0000000000001000 -!
b0000000000001000 5!
#249
#250
b0000000000001000 [
b0000000000000010 c
b0000 k
1s
b0000000000000001 5!
#251
b1111111111110111 #
b1111111111110111 -!
b1111111111110111 5!
#252
#253
b0000000000000110 [
b0000000000000111 c
b0110 k
#254
b0000000000000001 #
b1111111111111110 +
b01111111111111110 K
b0000000000000100 [
b0000000000000101 c
b0001 k
0s
b0000000000000001 -!
b1111111111111110 5!
#255
b1111111111111010 #
b0000000000000101 +
b00000000000000101 K
b0000000000000101 -!
b0000000000000101 5!
#256
#257
#258
b0000000000001010 [
b0000000000000111 c
b1111 k
1s
b1111111111111010 5!
#259
b0000000000001010 #
b0000000000001010 +
b00000000000001010 K
b0000000000001010 -!
b0000000000001010 5!
#260
#261
#262
b0000000000000110 [
b0000000000000110 c
b1010 k
0s
1=!
#263
b0000000000000110 #
b0000000000000101 +
13
1;
1C
b10000000000000101 K
1{
1%!
b0000000000000101 -!
b0000000000000101 5!
#264
#265
#266
#267
#268
#269
#270
#271
#272
#273
#274
1S
b0000000000000011 [
b0000000000000001 c
b1011 k
1s
b0000000000000110 5!
0=!
#275
b0000000000000001 #
b0000000000000001 +
03
0;
0C
b00000000000000001 K
0{
0%!
b0000000000000001 -!
b0000000000000001 5!
#276
#277
#278
#279
#280
#281
0S
b0000000000001000 [
b0000000000000000 c
b0100 k
0s
#282
b1111111111111111 #
b0000000000001000 +
b00000000000001000 K
b0000000000001000 -!
b0000000000001000 5!
#283
b0000000000000000 [
b0000000000000010 c
b1111 k
#284
b0000000000000000 #
b0000000000000000 +
b00000000000000000 K
1S
b0000000000000111 [
b0000000000000000 c
b0101 k
1s
b0000000000000000 -!
b0000000000000000 5!
#285
b1111111111111111 #
b0000000000001111 +
b00000000000001111 K
0S
b0000000000001001 [
b0000000000000001 c
b1111 k
b1111111111111111 -!
b1111111111111111 5!
#286
b0000000000001001 #
b0000000000001001 +
b00000000000001001 K
b0000000000001001 -!
b0000000000001001 5!
#287
b0000000000001000 [
b0000000000000011 c
b0111 k
#288
b0000000000001000 #
b0000000000001000 +
b00000000000001000 K
b0000000000001000 -!
b0000000000001000 5!
#289
#290
#291
#292
#293
#294
#295
#296
b0000000000001010 [
b1101 k
#297
b1111111111111110 #
b0000000000010101 +
b00000000000010101 K
b1111111111111110 -!
b1111111111111110 5!
#298
b0000000000000101 [
b0000000000000001 c
#299
b1111111111111111 #
b0000000000001010 +
b00000000000001010 K
b1111111111111111 -!
b1111111111111111 5!
