lvl_3/lvl3_lab01.sv
/* verilator lint_off DECLFILENAME */
module logic_unit #(
/* verilator lint_on DECLFILENAME */
    parameter WIDTH = 16
) (
    input wire [WIDTH-1:0] in_a,
    input wire [WIDTH-1:0] in_b,
    input wire [3:0]       select,
    output wire [WIDTH-1:0] logic_out
    
);

    logic [WIDTH-1:0] res;

    always_comb begin
        case (select)
            4'h0: res = ~in_a;
            4'h1: res = ~(in_a | in_b); 
            4'h2: res = ~in_a & in_b; 
            4'h3: res = 16'h0; 
            4'h4: res = ~(in_a & in_b); 
            4'h5: res = ~in_b; 
            4'h6: res = in_a ^ in_b; 
            4'h7: res = in_a & ~in_b; 
            4'h8: res = ~in_a | in_b; 
            4'h9: res = ~(in_a ^ in_b); 
            4'hA: res = in_b; 
            4'hB: res = in_a & in_b; 
            4'hC: res = 16'h1; 
            4'hD: res = in_a | ~in_b; 
            4'hE: res = in_a | in_b; 
            4'hF: res = in_a; 
            default: res = 16'h0;
        endcase
    end
    /*
    0000 0000 0000 1000
    0000 0000 0000 1001
    
    0000 0000 0000 1001
    */

    assign logic_out = res;

endmodule

module arithmetic #(
    parameter WIDTH = 16
) (
    input wire carry_in,
    input wire [WIDTH-1:0] in_a,
    input wire [WIDTH-1:0] in_b,
    input wire [3:0]       select,
    output wire cmp,
    output wire carry_out,
    output wire [WIDTH-1:0] arithmetic_out
);

    logic [WIDTH:0] extended_res;
    assign carry_out = 0;

    
                /*
                0000 0000 0000 1010
                0000 0000 0000 1001

                01111 1111 1111 0110
            or  00000 0000 0000 1010
                01111 1111 1111 1110

                */

    always_comb begin
        case (select)
            4'h0: extended_res = {1'b0, in_a}; // Extend in_a to 17 bits
            4'h1: extended_res = {1'b0, in_a} | {1'b0, in_b}; // Extend both to 17 bits
            4'h2: extended_res = {1'b0, in_a} | {1'b0, ~in_b}; // Extend both to 17 bits
            4'h3: extended_res = ~{{WIDTH{1'b0}}, 1'b1} + 1; // 17-bit zero
            4'h4: extended_res = {1'b0, in_a} | ({1'b0, in_a} & {1'b0, ~in_b}); // Extend all to 17 bits
            4'h5: extended_res = {1'b0, (in_a | in_b) + (in_a & ~in_b)} + {{WIDTH{1'b0}}, carry_in};
            4'h6: extended_res = {1'b0, in_a} + {1'b0, ~in_b}; // Extend both to 17 bits
            4'h7: extended_res = {1'b0, in_a & ~in_b}; // Extend to 17 bits
            4'h8: extended_res = {1'b0, in_a} + {1'b0, in_a & in_b} + {{WIDTH{1'b0}}, carry_in}; // Extend to 17 bits
            4'h9: extended_res = {1'b0, in_a} + {1'b0, in_b} + {{WIDTH{1'b0}}, carry_in}; // Extend to 17 bits
            4'hA: extended_res = {1'b0, in_a | ~in_b} + {1'b0, in_a & in_b} + {{WIDTH{1'b0}}, carry_in}; // Extend to 17 bits
            4'hB: extended_res = {1'b0, in_a & in_b}; // Extend to 17 bits
            4'hC: extended_res = {1'b0, in_a} + {1'b0, in_a} + {{WIDTH{1'b0}}, carry_in}; // Extend to 17 bits
            4'hD: extended_res = {1'b0, in_a | in_b} + {1'b0, in_a} + {{WIDTH{1'b0}}, carry_in}; // Extend to 17 bits
            4'hE: extended_res = {1'b0, in_a | ~in_b} + {1'b0, in_a} + {{WIDTH{1'b0}}, carry_in}; // Extend to 17 bits
            4'hF: extended_res = {1'b0, in_a} + {{WIDTH{1'b0}}, carry_in}; // Extend to 17 bits
            default: extended_res = {WIDTH+1{1'b0}}; // 17-bit zero
        endcase
    end
    /*
    
    0000 0000 0000 0001

    1111 1111 1111 1110
    0000 0000 0000 0011
    1111 1111 1111 1111

    0001
    0111
    
    1000
    0001

    1001
    0001
    1010
    */

    assign arithmetic_out = extended_res[WIDTH-1:0];
    assign carry_out = extended_res[WIDTH];
    assign cmp = (in_a == in_b) ? 1 : 0;

endmodule

module alu #(
    parameter WIDTH = 16
) (
    //input clk,
    //input rst,

    //input  operation_t  op_in, //instead of select ig -> could it be used?
    input  wire         carry_in,
    input  wire [WIDTH-1:0]  a_in,
    input  wire [WIDTH-1:0]  b_in,
    input  wire [3:0]        select,
    input  wire              mode,
    
    output wire              carry_out,
    output wire              compare,
    output wire [WIDTH-1:0]  alu_out
);

    logic [WIDTH-1:0] res;
    logic [WIDTH-1:0] logic_res;
    logic [WIDTH-1:0] arithmetic_res;
    logic car_out, car_arith;
    logic cmp, cmp_ari;

    logic_unit u1 (
        .in_a(a_in),
        .in_b(b_in),
        .select(select),
        .logic_out(logic_res)
    );

    arithmetic u2 (
        .in_a(a_in),
        .in_b(b_in),
        .select(select),
        .carry_in(carry_in),
        .arithmetic_out(arithmetic_res),
        .cmp(cmp_ari),
        .carry_out(car_arith)
    );
    always begin
        if(a_in == b_in) begin
            cmp = 1;
        end
        else begin
            cmp = 0;
        end
    end


    always_comb begin
        if(mode == 1) begin
            res = logic_res;
            car_out = 0;
        end else begin
            res = arithmetic_res;
            cmp = cmp_ari;
            car_out = car_arith;
        end
    end

    assign carry_out = car_out;
    assign alu_out = res;
    assign compare = cmp;

endmodule

lvl_3/waveform.vcd
$version Generated by VerilatedVcd $end
$date Tue Jun 25 18:05:17 2024
 $end
$timescale   1ns $end

 $scope module TOP $end
  $var wire 16 [ a_in [15:0] $end
  $var wire 16 -! alu_out [15:0] $end
  $var wire 16 c b_in [15:0] $end
  $var wire  1 S carry_in $end
  $var wire  1 { carry_out $end
  $var wire  1 %! compare $end
  $var wire  1 s mode $end
  $var wire  4 k select [3:0] $end
  $scope module alu $end
   $var wire 32 E! WIDTH [31:0] $end
   $var wire 16 [ a_in [15:0] $end
   $var wire 16 -! alu_out [15:0] $end
   $var wire 16 + arithmetic_res [15:0] $end
   $var wire 16 c b_in [15:0] $end
   $var wire  1 ; car_arith $end
   $var wire  1 3 car_out $end
   $var wire  1 S carry_in $end
   $var wire  1 { carry_out $end
   $var wire  1 C cmp $end
   $var wire  1 =! cmp_ari $end
   $var wire  1 %! compare $end
   $var wire 16 # logic_res [15:0] $end
   $var wire  1 s mode $end
   $var wire 16 5! res [15:0] $end
   $var wire  4 k select [3:0] $end
   $scope module u1 $end
    $var wire 32 E! WIDTH [31:0] $end
    $var wire 16 [ in_a [15:0] $end
    $var wire 16 c in_b [15:0] $end
    $var wire 16 # logic_out [15:0] $end
    $var wire 16 # res [15:0] $end
    $var wire  4 k select [3:0] $end
   $upscope $end
   $scope module u2 $end
    $var wire 32 E! WIDTH [31:0] $end
    $var wire 16 + arithmetic_out [15:0] $end
    $var wire  1 S carry_in $end
    $var wire  1 ; carry_out $end
    $var wire  1 =! cmp $end
    $var wire 17 K extended_res [16:0] $end
    $var wire 16 [ in_a [15:0] $end
    $var wire 16 c in_b [15:0] $end
    $var wire  4 k select [3:0] $end
   $upscope $end
  $upscope $end
 $upscope $end
$enddefinitions $end


#0
b0100111100100000 #
b1011000011011111 +
03
0;
0C
b01011000011011111 K
1S
b1011000001011001 [
b0011000011011110 c
b0001 k
1s
0{
0%!
b0100111100100000 -!
b0100111100100000 5!
0=!
b00000000000000000000000000010000 E!
#1
#2
#3
#4
#5
#6
#7
0S
b0000000000000110 [
b0000000000000101 c
b0000 k
0s
b1011000011011111 5!
#8
b1111111111111001 #
b0000000000000110 +
b00000000000000110 K
b0000000000000110 -!
b0000000000000110 5!
#9
1S
b0000000000000100 [
b0000000000000111 c
b0110 k
#10
b0000000000000011 #
b1111111111111100 +
b01111111111111100 K
b1111111111111100 -!
b1111111111111100 5!
#11
#12
#13
#14
#15
#16
#17
b0000000000001010 [
b0000000000001000 c
b1100 k
#18
b0000000000000001 #
b0000000000010101 +
b00000000000010101 K
b0000000000010101 -!
b0000000000010101 5!
#19
b0000000000000101 [
b0000000000000000 c
#20
b0000000000001011 +
b00000000000001011 K
b0000000000001011 -!
b0000000000001011 5!
#21
#22
#23
b0000000000000110 [
b0000000000000111 c
b0001 k
#24
b1111111111111000 #
b0000000000000111 +
b00000000000000111 K
b0000000000000111 -!
b0000000000000111 5!
#25
0S
b0000000000001001 [
b0000000000000000 c
b0101 k
#26
b1111111111111111 #
b0000000000010010 +
b00000000000010010 K
b0000000000010010 -!
b0000000000010010 5!
#27
#28
#29
#30
#31
#32
b0000000000000001 [
b0100 k
#33
b0000000000000001 +
b00000000000000001 K
b0000000000000001 -!
b0000000000000001 5!
#34
b0000000000000011 [
b0000000000001000 c
b0111 k
1s
b1111111111111111 5!
#35
b0000000000000011 #
b0000000000000011 +
b00000000000000011 K
b0000000000000011 -!
b0000000000000011 5!
#36
b0000000000000010 [
b0000000000000111 c
b1100 k
#37
b0000000000000001 #
b0000000000000100 +
b00000000000000100 K
1S
b0000000000001010 [
b0000000000000011 c
b0010 k
b0000000000000001 -!
b0000000000000001 5!
#38
b1111111111111110 +
b01111111111111110 K
0S
b0000000000001001 c
b1000 k
#39
b1111111111111101 #
b0000000000010010 +
b00000000000010010 K
b1111111111111101 -!
b1111111111111101 5!
#40
#41
#42
#43
#44
1S
b0000000000000101 [
b0000000000000111 c
#45
b1111111111111111 #
b0000000000001011 +
b00000000000001011 K
b1111111111111111 -!
b1111111111111111 5!
#46
b0000000000000111 [
b0110 k
0s
b0000000000001011 5!
1=!
#47
b0000000000000000 #
b1111111111111111 +
1C
b01111111111111111 K
1%!
b1111111111111111 5!
#48
0S
b0000000000000101 [
b0000000000000101 c
b0010 k
1s
b0000000000000000 5!
#49
b0000000000000000 -!
#50
b0000000000000111 [
b0000000000000001 c
b1100 k
0=!
#51
b0000000000000001 #
b0000000000001110 +
0C
b00000000000001110 K
0%!
b0000000000000001 -!
b0000000000000001 5!
#52
1S
b0000000000000000 [
b0000000000000101 c
b0111 k
#53
b0000000000000000 #
b0000000000000000 +
b00000000000000000 K
b0000000000000000 -!
b0000000000000000 5!
#54
#55
#56
#57
#58
0S
b0000000000000111 [
b0000000000000011 c
b0000 k
#59
b1111111111111000 #
b0000000000000111 +
b00000000000000111 K
b1111111111111000 -!
b1111111111111000 5!
#60
#61
#62
#63
#64
1S
b0000000000000001 [
b0000000000000000 c
b1111 k
0s
b0000000000000111 5!
#65
b0000000000000001 #
b0000000000000010 +
b00000000000000010 K
b0000000000000010 -!
b0000000000000010 5!
#66
#67
#68
#69
0S
b0000000000000100 [
b0000000000000111 c
#70
b0000000000000100 #
b0000000000000100 +
b00000000000000100 K
b0000000000000100 -!
b0000000000000100 5!
#71
#72
b0000000000000010 [
b0000000000000101 c
b1010 k
1s
#73
b0000000000000101 #
b1111111111111010 +
b01111111111111010 K
b0000000000000101 -!
b0000000000000101 5!
#74
#75
#76
#77
#78
b0000000000000000 [
b0000000000000011 c
b0011 k
#79
b0000000000000000 #
b1111111111111111 +
1;
b11111111111111111 K
b0000000000000000 -!
b0000000000000000 5!
#80
1S
b0000000000000111 [
b0000000000000101 c
b0111 k
#81
b0000000000000010 #
b0000000000000010 +
0;
b00000000000000010 K
b0000000000000010 -!
b0000000000000010 5!
#82
0S
b0000000000001001 [
b0000000000000111 c
b0010 k
#83
b0000000000000110 #
b1111111111111001 +
b01111111111111001 K
b0000000000000110 -!
b0000000000000110 5!
#84
#85
#86
#87
#88
#89
#90
#91
#92
#93
#94
1S
b0000000000000101 [
b1110 k
0s
b1111111111111001 5!
#95
b0000000000000111 #
b0000000000000011 +
13
1;
b10000000000000011 K
1{
b0000000000000011 -!
b0000000000000011 5!
#96
0S
b0000000000001001 [
b0000000000000100 c
b1000 k
1s
b0000000000000111 5!
#97
b1111111111110110 #
b0000000000001001 +
03
0;
b00000000000001001 K
0{
b1111111111110110 -!
b1111111111110110 5!
#98
#99
1S
b0000000000000010 [
b0000000000000111 c
b1001 k
#100
b1111111111111010 #
b0000000000001010 +
b00000000000001010 K
0S
b0000000000000100 [
b0000000000000110 c
b0001 k
b1111111111111010 -!
b1111111111111010 5!
#101
b1111111111111001 #
b0000000000000110 +
b00000000000000110 K
b0000000000000011 [
b0000000000001010 c
b0101 k
b1111111111111001 -!
b1111111111111001 5!
#102
b1111111111110101 #
b0000000000001100 +
b00000000000001100 K
b1111111111110101 -!
b1111111111110101 5!
#103
#104
b0000000000000010 [
b0000000000000000 c
#105
b1111111111111111 #
b0000000000000100 +
b00000000000000100 K
b1111111111111111 -!
b1111111111111111 5!
#106
#107
#108
#109
#110
#111
#112
#113
1S
b0000000000000000 [
b0000000000000111 c
b0010 k
0s
b0000000000000100 5!
#114
b0000000000000111 #
b1111111111111000 +
b01111111111111000 K
b1111111111111000 -!
b1111111111111000 5!
#115
0S
b0000000000000100 [
b0000000000000001 c
b0001 k
1s
b0000000000000111 5!
#116
b1111111111111010 #
b0000000000000101 +
b00000000000000101 K
b1111111111111010 -!
b1111111111111010 5!
#117
b0000000000000111 [
b0000000000000010 c
b1010 k
0s
b0000000000000101 5!
#118
b0000000000000010 #
b0000000000000001 +
13
1;
b10000000000000001 K
1{
b0000000000000001 -!
b0000000000000001 5!
#119
#120
#121
#122
#123
#124
#125
b0000000000000001 [
b0000000000001000 c
b1111 k
#126
b0000000000000001 #
03
0;
b00000000000000001 K
0{
#127
#128
#129
#130
#131
#132
#133
#134
#135
#136
#137
1S
b0000000000000101 c
b0000 k
1s
#138
b1111111111111110 #
b1111111111111110 -!
b1111111111111110 5!
#139
0S
b0000000000000100 [
b0000000000000010 c
b1000 k
#140
b1111111111111011 #
b0000000000000100 +
b00000000000000100 K
b1111111111111011 -!
b1111111111111011 5!
#141
#142
#143
#144
1S
b0000000000001010 c
b1111 k
0s
b0000000000000100 5!
#145
b0000000000000100 #
b0000000000000101 +
b00000000000000101 K
b0000000000000101 -!
b0000000000000101 5!
#146
#147
#148
#149
#150
#151
#152
#153
#154
#155
#156
#157
#158
#159
#160
#161
0S
b0000000000001000 [
b0000000000000001 c
b1100 k
1s
b0000000000000100 5!
#162
b0000000000000001 #
b0000000000010000 +
b00000000000010000 K
b0000000000000001 -!
b0000000000000001 5!
#163
#164
#165
#166
#167
#168
#169
#170
#171
b0000000000000111 [
b0000000000001010 c
b1010 k
#172
b0000000000001010 #
b1111111111111001 +
b01111111111111001 K
b0000000000001010 -!
b0000000000001010 5!
#173
#174
#175
#176
#177
#178
#179
#180
1S
b0000000000000001 c
b1001 k
0s
b1111111111111001 5!
#181
b1111111111111001 #
b0000000000001001 +
b00000000000001001 K
b0000000000000011 [
b0000000000001000 c
b0010 k
b0000000000001001 -!
b0000000000001001 5!
#182
b0000000000001000 #
b1111111111110111 +
b01111111111110111 K
b1111111111110111 -!
b1111111111110111 5!
#183
#184
#185
#186
#187
#188
#189
#190
#191
#192
#193
#194
#195
#196
b0000000000000110 [
b0000000000000100 c
b1110 k
1s
b0000000000001000 5!
#197
b0000000000000110 #
b0000000000000110 +
1;
b10000000000000110 K
b0000000000000110 -!
b0000000000000110 5!
#198
#199
#200
#201
#202
#203
b0000000000000110 c
b0100 k
1=!
#204
b1111111111111001 #
0;
1C
b00000000000000110 K
1%!
b1111111111111001 -!
b1111111111111001 5!
#205
#206
b0000000000000100 [
b0111 k
0=!
#207
b0000000000000000 #
b0000000000000000 +
0C
b00000000000000000 K
0%!
b0000000000000000 -!
b0000000000000000 5!
#208
#209
0S
b0000000000000111 [
b0000000000000111 c
b1010 k
1=!
#210
b0000000000000111 #
b0000000000000110 +
1;
1C
b10000000000000110 K
1%!
b0000000000000111 -!
b0000000000000111 5!
#211
#212
b0000000000000100 [
b1000 k
0s
b0000000000000110 5!
0=!
#213
b1111111111111111 #
b0000000000001000 +
0;
0C
b00000000000001000 K
0%!
b0000000000001000 -!
b0000000000001000 5!
#214
#215
#216
b0000000000001010 [
b0000000000000100 c
b1101 k
#217
b1111111111111011 #
b0000000000011000 +
b00000000000011000 K
b0000000000011000 -!
b0000000000011000 5!
#218
#219
#220
#221
#222
#223
#224
#225
#226
#227
#228
#229
#230
#231
1S
b0000000000000100 [
b1010 k
1=!
#232
b0000000000000100 #
b0000000000000100 +
13
1;
1C
b10000000000000100 K
1{
1%!
b0000000000000100 -!
b0000000000000100 5!
#233
#234
#235
#236
0S
b0000000000001010 [
b0000000000000111 c
b1001 k
0=!
#237
b1111111111110010 #
b0000000000010001 +
03
0;
0C
b00000000000010001 K
1S
b0000000000000000 [
b0000000000000011 c
b0010 k
1s
0{
0%!
b0000000000010001 -!
b1111111111110010 5!
#238
b0000000000000011 #
b1111111111111100 +
b01111111111111100 K
b0000000000000011 -!
b0000000000000011 5!
#239
#240
#241
#242
#243
#244
#245
#246
#247
b0000000000000101 [
b0101 k
#248
b1111111111111100 #
b0000000000001100 +
b00000000000001100 K
b1111111111111100 -!
b1111111111111100 5!
#249
#250
b0000000000000100 [
b0000000000000110 c
b0011 k
0s
b0000000000001100 5!
#251
b0000000000000000 #
b1111111111111111 +
13
1;
b11111111111111111 K
1{
b1111111111111111 -!
b1111111111111111 5!
#252
#253
#254
#255
#256
#257
#258
#259
#260
#261
#262
#263
#264
#265
#266
#267
0S
b0000000000001010 [
1s
b0000000000000000 5!
#268
03
b0000000000000001 [
b0000000000000000 c
b1010 k
0s
0{
b0000000000000000 -!
b1111111111111111 5!
#269
0;
b01111111111111111 K
b1111111111111111 -!
#270
#271
#272
#273
#274
1S
b0000000000000111 [
b0000000000000100 c
b1100 k
#275
b0000000000000001 #
b0000000000001111 +
b00000000000001111 K
b0000000000001111 -!
b0000000000001111 5!
#276
#277
#278
#279
#280
#281
#282
#283
#284
#285
0S
b0000000000001001 [
b0000000000000101 c
b0101 k
#286
b1111111111111010 #
b0000000000010101 +
b00000000000010101 K
b0000000000010101 -!
b0000000000010101 5!
#287
#288
#289
#290
1S
b0000000000001000 [
b0000000000000110 c
b0000 k
#291
b1111111111110111 #
b0000000000001000 +
b00000000000001000 K
b0000000000001000 -!
b0000000000001000 5!
#292
#293
#294
#295
b0000000000000000 [
b0000000000001010 c
b1101 k
1s
b1111111111110111 5!
#296
b1111111111110101 #
b0000000000001011 +
b00000000000001011 K
b1111111111110101 -!
b1111111111110101 5!
#297
0S
b0000000000000011 [
b0000000000000100 c
b0010 k
#298
b0000000000000100 #
b1111111111111011 +
b01111111111111011 K
b0000000000000100 -!
b0000000000000100 5!
