lvl3/lab3/prelab.sv
module prelab (
    input clk, 
    input reset, // Asynchronous reset
    output reg [2:0] light // Traffic light output : 3'b001 (RED), 3'b010 (GREEN), 3'b100 (YELLOW)
);

    parameter RED = 2'b00;
    parameter GREEN = 2'b01;
    parameter YELLOW = 2'b10;
    parameter CLOCK_FREQ = 50;
    parameter DURATION = 5;
/* verilator lint_off UNOPTFLAT */
    reg [31:0] counter; // Adjusted to 32 bits
    reg [1:0] current_state, next_state;

    // Model state register (sequential logic)
    always @(posedge clk or posedge reset) begin
        if (reset) begin
            current_state <= RED;
            /* verilator lint_off BLKSEQ */
            counter =  0;
        end else begin
            current_state <= next_state;
            counter =  counter + 1;
        end
    end

    // Model next state decode logic (combinational logic)
    always @(*) begin
        case (current_state)
            RED: begin
                if (counter == CLOCK_FREQ * DURATION * 10) begin
                    next_state = GREEN;
                    counter =  0; // Reset counter
                end else begin
                    next_state = RED;
                end
            end
            GREEN: begin
                if (counter == CLOCK_FREQ * DURATION * 10) begin
                    next_state = YELLOW;
                    counter =  0; // Reset counter
                end else begin
                    next_state = GREEN;
                end
            end
            YELLOW: begin
                if (counter == CLOCK_FREQ * DURATION) begin
                    next_state = RED;
                    counter =  0; // Reset counter
                end else begin
                    next_state = YELLOW;
                end
            end
            default: begin
                next_state = RED;
                counter =  0; // Reset counter
            end
        endcase
    end

    // Model output logic (combinational logic)
    always @(*) begin
        case (current_state)
            RED: begin
                light = 3'b001; // RED light
            end
            GREEN: begin
                light = 3'b010; // GREEN light
            end
            YELLOW: begin
                light = 3'b100; // YELLOW light
            end
            default: begin
                light = 3'b001; // default to RED light
            end
        endcase
    end

endmodule

lvl_3/lab3/traffic_light_fsm.vcd
$version Generated by VerilatedVcd $end
$date Wed Jun 19 13:11:47 2024
 $end
$timescale   1ns $end

 $scope module TOP $end
  $var wire  1 ; clk $end
  $var wire  3 K light [2:0] $end
  $var wire  1 C reset $end
  $scope module prelab $end
   $var wire 32 k CLOCK_FREQ [31:0] $end
   $var wire 32 s DURATION [31:0] $end
   $var wire  2 [ GREEN [1:0] $end
   $var wire  2 S RED [1:0] $end
   $var wire  2 c YELLOW [1:0] $end
   $var wire  1 ; clk $end
   $var wire 32 # counter [31:0] $end
   $var wire  2 3 current_state [1:0] $end
   $var wire  3 K light [2:0] $end
   $var wire  2 + next_state [1:0] $end
   $var wire  1 C reset $end
  $upscope $end
 $upscope $end
$enddefinitions $end


#0
b00000000000000000000000000000000 #
b00 +
b11 3
1;
1C
b001 K
b00 S
b01 [
b10 c
b00000010111110101111000010000000 k
b00000000000000000000000000000101 s
#1
0;
#2
b00000000000000000000000000000001 #
b00 3
1;
0C
#3
0;
#4
b00000000000000000000000000000010 #
1;
#5
0;
#6
b00000000000000000000000000000011 #
1;
#7
0;
#8
b00000000000000000000000000000100 #
1;
#9
0;
#10
b00000000000000000000000000000101 #
1;
#11
0;
#12
b00000000000000000000000000000110 #
1;
#13
0;
#14
b00000000000000000000000000000111 #
1;
#15
0;
#16
b00000000000000000000000000001000 #
1;
#17
0;
#18
b00000000000000000000000000001001 #
1;
#19
0;
#20
b00000000000000000000000000001010 #
1;
#21
0;
#22
b00000000000000000000000000001011 #
1;
#23
0;
#24
b00000000000000000000000000001100 #
1;
#25
0;
#26
b00000000000000000000000000001101 #
1;
#27
0;
#28
b00000000000000000000000000001110 #
1;
#29
0;
#30
b00000000000000000000000000001111 #
1;
#31
0;
#32
b00000000000000000000000000010000 #
1;
#33
0;
#34
b00000000000000000000000000010001 #
1;
#35
0;
#36
b00000000000000000000000000010010 #
1;
#37
0;
#38
b00000000000000000000000000010011 #
1;
#39
0;
#40
b00000000000000000000000000010100 #
1;
#41
0;
#42
b00000000000000000000000000010101 #
1;
#43
0;
#44
b00000000000000000000000000010110 #
1;
#45
0;
#46
b00000000000000000000000000010111 #
1;
#47
0;
#48
b00000000000000000000000000011000 #
1;
#49
0;
#50
b00000000000000000000000000011001 #
1;
#51
0;
#52
b00000000000000000000000000011010 #
1;
#53
0;
#54
b00000000000000000000000000011011 #
1;
#55
0;
#56
b00000000000000000000000000011100 #
1;
#57
0;
#58
b00000000000000000000000000011101 #
1;
#59
0;
#60
b00000000000000000000000000011110 #
1;
#61
0;
#62
b00000000000000000000000000011111 #
1;
#63
0;
#64
b00000000000000000000000000100000 #
1;
#65
0;
#66
b00000000000000000000000000100001 #
1;
#67
0;
#68
b00000000000000000000000000100010 #
1;
#69
0;
#70
b00000000000000000000000000100011 #
1;
#71
0;
#72
b00000000000000000000000000100100 #
1;
#73
0;
#74
b00000000000000000000000000100101 #
1;
#75
0;
#76
b00000000000000000000000000100110 #
1;
#77
0;
#78
b00000000000000000000000000100111 #
1;
#79
0;
#80
b00000000000000000000000000101000 #
1;
#81
0;
#82
b00000000000000000000000000101001 #
1;
#83
0;
#84
b00000000000000000000000000101010 #
1;
#85
0;
#86
b00000000000000000000000000101011 #
1;
#87
0;
#88
b00000000000000000000000000101100 #
1;
#89
0;
#90
b00000000000000000000000000101101 #
1;
#91
0;
#92
b00000000000000000000000000101110 #
1;
#93
0;
#94
b00000000000000000000000000101111 #
1;
#95
0;
#96
b00000000000000000000000000110000 #
1;
#97
0;
#98
b00000000000000000000000000110001 #
1;
#99
0;
#100
b00000000000000000000000000110010 #
1;
#101
0;
#102
b00000000000000000000000000110011 #
1;
#103
0;
#104
b00000000000000000000000000110100 #
1;
#105
0;
#106
b00000000000000000000000000110101 #
1;
#107
0;
#108
b00000000000000000000000000110110 #
1;
#109
0;
#110
b00000000000000000000000000110111 #
1;
#111
0;
#112
b00000000000000000000000000111000 #
1;
#113
0;
#114
b00000000000000000000000000111001 #
1;
#115
0;
#116
b00000000000000000000000000111010 #
1;
#117
0;
#118
b00000000000000000000000000111011 #
1;
#119
0;
#120
b00000000000000000000000000111100 #
1;
#121
0;
#122
b00000000000000000000000000111101 #
1;
#123
0;
#124
b00000000000000000000000000111110 #
1;
#125
0;
#126
b00000000000000000000000000111111 #
1;
#127
0;
#128
b00000000000000000000000001000000 #
1;
#129
0;
#130
b00000000000000000000000001000001 #
1;
#131
0;
#132
b00000000000000000000000001000010 #
1;
#133
0;
#134
b00000000000000000000000001000011 #
1;
#135
0;
#136
b00000000000000000000000001000100 #
1;
#137
0;
#138
b00000000000000000000000001000101 #
1;
#139
0;
#140
b00000000000000000000000001000110 #
1;
#141
0;
#142
b00000000000000000000000001000111 #
1;
#143
0;
#144
b00000000000000000000000001001000 #
1;
#145
0;
#146
b00000000000000000000000001001001 #
1;
#147
0;
#148
b00000000000000000000000001001010 #
1;
#149
0;
#150
b00000000000000000000000001001011 #
1;
#151
0;
#152
b00000000000000000000000001001100 #
1;
#153
0;
#154
b00000000000000000000000001001101 #
1;
#155
0;
#156
b00000000000000000000000001001110 #
1;
#157
0;
#158
b00000000000000000000000001001111 #
1;
#159
0;
#160
b00000000000000000000000001010000 #
1;
#161
0;
#162
b00000000000000000000000001010001 #
1;
#163
0;
#164
b00000000000000000000000001010010 #
1;
#165
0;
#166
b00000000000000000000000001010011 #
1;
#167
0;
#168
b00000000000000000000000001010100 #
1;
#169
0;
#170
b00000000000000000000000001010101 #
1;
#171
0;
#172
b00000000000000000000000001010110 #
1;
#173
0;
#174
b00000000000000000000000001010111 #
1;
#175
0;
#176
b00000000000000000000000001011000 #
1;
#177
0;
#178
b00000000000000000000000001011001 #
1;
#179
0;
#180
b00000000000000000000000001011010 #
1;
#181
0;
#182
b00000000000000000000000001011011 #
1;
#183
0;
#184
b00000000000000000000000001011100 #
1;
#185
0;
#186
b00000000000000000000000001011101 #
1;
#187
0;
#188
b00000000000000000000000001011110 #
1;
#189
0;
#190
b00000000000000000000000001011111 #
1;
#191
0;
#192
b00000000000000000000000001100000 #
1;
#193
0;
#194
b00000000000000000000000001100001 #
1;
#195
0;
#196
b00000000000000000000000001100010 #
1;
#197
0;
#198
b00000000000000000000000001100011 #
1;
#199
0;
#200
b00000000000000000000000001100100 #
1;
#201
0;
#202
b00000000000000000000000001100101 #
1;
#203
0;
#204
b00000000000000000000000001100110 #
1;
#205
0;
#206
b00000000000000000000000001100111 #
1;
#207
0;
#208
b00000000000000000000000001101000 #
1;
#209
0;
#210
b00000000000000000000000001101001 #
1;
#211
0;
#212
b00000000000000000000000001101010 #
1;
#213
0;
#214
b00000000000000000000000001101011 #
1;
#215
0;
#216
b00000000000000000000000001101100 #
1;
#217
0;
#218
b00000000000000000000000001101101 #
1;
#219
0;
#220
b00000000000000000000000001101110 #
1;
#221
0;
#222
b00000000000000000000000001101111 #
1;
#223
0;
#224
b00000000000000000000000001110000 #
1;
#225
0;
#226
b00000000000000000000000001110001 #
1;
#227
0;
#228
b00000000000000000000000001110010 #
1;
#229
0;
#230
b00000000000000000000000001110011 #
1;
#231
0;
#232
b00000000000000000000000001110100 #
1;
#233
0;
#234
b00000000000000000000000001110101 #
1;
#235
0;
#236
b00000000000000000000000001110110 #
1;
#237
0;
#238
b00000000000000000000000001110111 #
1;
#239
0;
#240
b00000000000000000000000001111000 #
1;
#241
0;
#242
b00000000000000000000000001111001 #
1;
#243
0;
#244
b00000000000000000000000001111010 #
1;
#245
0;
#246
b00000000000000000000000001111011 #
1;
#247
0;
#248
b00000000000000000000000001111100 #
1;
#249
0;
#250
b00000000000000000000000001111101 #
1;
#251
0;
#252
b00000000000000000000000001111110 #
1;
#253
0;
#254
b00000000000000000000000001111111 #
1;
#255
0;
#256
b00000000000000000000000010000000 #
1;
#257
0;
#258
b00000000000000000000000010000001 #
1;
#259
0;
#260
b00000000000000000000000010000010 #
1;
#261
0;
#262
b00000000000000000000000010000011 #
1;
#263
0;
#264
b00000000000000000000000010000100 #
1;
#265
0;
#266
b00000000000000000000000010000101 #
1;
#267
0;
#268
b00000000000000000000000010000110 #
1;
#269
0;
#270
b00000000000000000000000010000111 #
1;
#271
0;
#272
b00000000000000000000000010001000 #
1;
#273
0;
#274
b00000000000000000000000010001001 #
1;
#275
0;
#276
b00000000000000000000000010001010 #
1;
#277
0;
#278
b00000000000000000000000010001011 #
1;
#279
0;
#280
b00000000000000000000000010001100 #
1;
#281
0;
#282
b00000000000000000000000010001101 #
1;
#283
0;
#284
b00000000000000000000000010001110 #
1;
#285
0;
#286
b00000000000000000000000010001111 #
1;
#287
0;
#288
b00000000000000000000000010010000 #
1;
#289
0;
#290
b00000000000000000000000010010001 #
1;
#291
0;
#292
b00000000000000000000000010010010 #
1;
#293
0;
#294
b00000000000000000000000010010011 #
1;
#295
0;
#296
b00000000000000000000000010010100 #
1;
#297
0;
#298
b00000000000000000000000010010101 #
1;
#299
0;
#300
b00000000000000000000000010010110 #
1;
#301
0;
#302
b00000000000000000000000010010111 #
1;
#303
0;
#304
b00000000000000000000000010011000 #
1;
#305
0;
#306
b00000000000000000000000010011001 #
1;
#307
0;
#308
b00000000000000000000000010011010 #
1;
#309
0;
#310
b00000000000000000000000010011011 #
1;
#311
0;
#312
b00000000000000000000000010011100 #
1;
#313
0;
#314
b00000000000000000000000010011101 #
1;
#315
0;
#316
b00000000000000000000000010011110 #
1;
#317
0;
#318
b00000000000000000000000010011111 #
1;
#319
0;
#320
b00000000000000000000000010100000 #
1;
#321
0;
#322
b00000000000000000000000010100001 #
1;
#323
0;
#324
b00000000000000000000000010100010 #
1;
#325
0;
#326
b00000000000000000000000010100011 #
1;
#327
0;
#328
b00000000000000000000000010100100 #
1;
#329
0;
#330
b00000000000000000000000010100101 #
1;
#331
0;
#332
b00000000000000000000000010100110 #
1;
#333
0;
#334
b00000000000000000000000010100111 #
1;
#335
0;
#336
b00000000000000000000000010101000 #
1;
#337
0;
#338
b00000000000000000000000010101001 #
1;
#339
0;
#340
b00000000000000000000000010101010 #
1;
#341
0;
#342
b00000000000000000000000010101011 #
1;
#343
0;
#344
b00000000000000000000000010101100 #
1;
#345
0;
#346
b00000000000000000000000010101101 #
1;
#347
0;
#348
b00000000000000000000000010101110 #
1;
#349
0;
#350
b00000000000000000000000010101111 #
1;
#351
0;
#352
b00000000000000000000000010110000 #
1;
#353
0;
#354
b00000000000000000000000010110001 #
1;
#355
0;
#356
b00000000000000000000000010110010 #
1;
#357
0;
#358
b00000000000000000000000010110011 #
1;
#359
0;
#360
b00000000000000000000000010110100 #
1;
#361
0;
#362
b00000000000000000000000010110101 #
1;
#363
0;
#364
b00000000000000000000000010110110 #
1;
#365
0;
#366
b00000000000000000000000010110111 #
1;
#367
0;
#368
b00000000000000000000000010111000 #
1;
#369
0;
#370
b00000000000000000000000010111001 #
1;
#371
0;
#372
b00000000000000000000000010111010 #
1;
#373
0;
#374
b00000000000000000000000010111011 #
1;
#375
0;
#376
b00000000000000000000000010111100 #
1;
#377
0;
#378
b00000000000000000000000010111101 #
1;
#379
0;
#380
b00000000000000000000000010111110 #
1;
#381
0;
#382
b00000000000000000000000010111111 #
1;
#383
0;
#384
b00000000000000000000000011000000 #
1;
#385
0;
#386
b00000000000000000000000011000001 #
1;
#387
0;
#388
b00000000000000000000000011000010 #
1;
#389
0;
#390
b00000000000000000000000011000011 #
1;
#391
0;
#392
b00000000000000000000000011000100 #
1;
#393
0;
#394
b00000000000000000000000011000101 #
1;
#395
0;
#396
b00000000000000000000000011000110 #
1;
#397
0;
#398
b00000000000000000000000011000111 #
1;
#399
0;
#400
b00000000000000000000000011001000 #
1;
#401
0;
#402
b00000000000000000000000011001001 #
1;
#403
0;
#404
b00000000000000000000000011001010 #
1;
#405
0;
#406
b00000000000000000000000011001011 #
1;
#407
0;
#408
b00000000000000000000000011001100 #
1;
#409
0;
#410
b00000000000000000000000011001101 #
1;
#411
0;
#412
b00000000000000000000000011001110 #
1;
#413
0;
#414
b00000000000000000000000011001111 #
1;
#415
0;
#416
b00000000000000000000000011010000 #
1;
#417
0;
#418
b00000000000000000000000011010001 #
1;
#419
0;
#420
b00000000000000000000000011010010 #
1;
#421
0;
#422
b00000000000000000000000011010011 #
1;
#423
0;
#424
b00000000000000000000000011010100 #
1;
#425
0;
#426
b00000000000000000000000011010101 #
1;
#427
0;
#428
b00000000000000000000000011010110 #
1;
#429
0;
#430
b00000000000000000000000011010111 #
1;
#431
0;
#432
b00000000000000000000000011011000 #
1;
#433
0;
#434
b00000000000000000000000011011001 #
1;
#435
0;
#436
b00000000000000000000000011011010 #
1;
#437
0;
#438
b00000000000000000000000011011011 #
1;
#439
0;
#440
b00000000000000000000000011011100 #
1;
#441
0;
#442
b00000000000000000000000011011101 #
1;
#443
0;
#444
b00000000000000000000000011011110 #
1;
#445
0;
#446
b00000000000000000000000011011111 #
1;
#447
0;
#448
b00000000000000000000000011100000 #
1;
#449
0;
#450
b00000000000000000000000011100001 #
1;
#451
0;
#452
b00000000000000000000000011100010 #
1;
#453
0;
#454
b00000000000000000000000011100011 #
1;
#455
0;
#456
b00000000000000000000000011100100 #
1;
#457
0;
#458
b00000000000000000000000011100101 #
1;
#459
0;
#460
b00000000000000000000000011100110 #
1;
#461
0;
#462
b00000000000000000000000011100111 #
1;
#463
0;
#464
b00000000000000000000000011101000 #
1;
#465
0;
#466
b00000000000000000000000011101001 #
1;
#467
0;
#468
b00000000000000000000000011101010 #
1;
#469
0;
#470
b00000000000000000000000011101011 #
1;
#471
0;
#472
b00000000000000000000000011101100 #
1;
#473
0;
#474
b00000000000000000000000011101101 #
1;
#475
0;
#476
b00000000000000000000000011101110 #
1;
#477
0;
#478
b00000000000000000000000011101111 #
1;
#479
0;
#480
b00000000000000000000000011110000 #
1;
#481
0;
#482
b00000000000000000000000011110001 #
1;
#483
0;
#484
b00000000000000000000000011110010 #
1;
#485
0;
#486
b00000000000000000000000011110011 #
1;
#487
0;
#488
b00000000000000000000000011110100 #
1;
#489
0;
#490
b00000000000000000000000011110101 #
1;
#491
0;
#492
b00000000000000000000000011110110 #
1;
#493
0;
#494
b00000000000000000000000011110111 #
1;
#495
0;
#496
b00000000000000000000000011111000 #
1;
#497
0;
#498
b00000000000000000000000011111001 #
1;
#499
0;
#500
b00000000000000000000000011111010 #
1;
#501
0;
#502
b00000000000000000000000011111011 #
1;
#503
0;
#504
b00000000000000000000000011111100 #
1;
#505
0;
#506
b00000000000000000000000011111101 #
1;
#507
0;
#508
b00000000000000000000000011111110 #
1;
#509
0;
#510
b00000000000000000000000011111111 #
1;
#511
0;
#512
b00000000000000000000000100000000 #
1;
#513
0;
#514
b00000000000000000000000100000001 #
1;
#515
0;
#516
b00000000000000000000000100000010 #
1;
#517
0;
#518
b00000000000000000000000100000011 #
1;
#519
0;
#520
b00000000000000000000000100000100 #
1;
#521
0;
#522
b00000000000000000000000100000101 #
1;
#523
0;
#524
b00000000000000000000000100000110 #
1;
#525
0;
#526
b00000000000000000000000100000111 #
1;
#527
0;
#528
b00000000000000000000000100001000 #
1;
#529
0;
#530
b00000000000000000000000100001001 #
1;
#531
0;
#532
b00000000000000000000000100001010 #
1;
#533
0;
#534
b00000000000000000000000100001011 #
1;
#535
0;
#536
b00000000000000000000000100001100 #
1;
#537
0;
#538
b00000000000000000000000100001101 #
1;
#539
0;
#540
b00000000000000000000000100001110 #
1;
#541
0;
#542
b00000000000000000000000100001111 #
1;
#543
0;
#544
b00000000000000000000000100010000 #
1;
#545
0;
#546
b00000000000000000000000100010001 #
1;
#547
0;
#548
b00000000000000000000000100010010 #
1;
#549
0;
#550
b00000000000000000000000100010011 #
1;
#551
0;
#552
b00000000000000000000000100010100 #
1;
#553
0;
#554
b00000000000000000000000100010101 #
1;
#555
0;
#556
b00000000000000000000000100010110 #
1;
#557
0;
#558
b00000000000000000000000100010111 #
1;
#559
0;
#560
b00000000000000000000000100011000 #
1;
#561
0;
#562
b00000000000000000000000100011001 #
1;
#563
0;
#564
b00000000000000000000000100011010 #
1;
#565
0;
#566
b00000000000000000000000100011011 #
1;
#567
0;
#568
b00000000000000000000000100011100 #
1;
#569
0;
#570
b00000000000000000000000100011101 #
1;
#571
0;
#572
b00000000000000000000000100011110 #
1;
#573
0;
#574
b00000000000000000000000100011111 #
1;
#575
0;
#576
b00000000000000000000000100100000 #
1;
#577
0;
#578
b00000000000000000000000100100001 #
1;
#579
0;
#580
b00000000000000000000000100100010 #
1;
#581
0;
#582
b00000000000000000000000100100011 #
1;
#583
0;
#584
b00000000000000000000000100100100 #
1;
#585
0;
#586
b00000000000000000000000100100101 #
1;
#587
0;
#588
b00000000000000000000000100100110 #
1;
#589
0;
#590
b00000000000000000000000100100111 #
1;
#591
0;
#592
b00000000000000000000000100101000 #
1;
#593
0;
#594
b00000000000000000000000100101001 #
1;
#595
0;
#596
b00000000000000000000000100101010 #
1;
#597
0;
#598
b00000000000000000000000100101011 #
1;
#599
0;
#600
b00000000000000000000000100101100 #
1;
#601
0;
#602
b00000000000000000000000100101101 #
1;
#603
0;
#604
b00000000000000000000000100101110 #
1;
#605
0;
#606
b00000000000000000000000100101111 #
1;
#607
0;
#608
b00000000000000000000000100110000 #
1;
#609
0;
#610
b00000000000000000000000100110001 #
1;
#611
0;
#612
b00000000000000000000000100110010 #
1;
#613
0;
#614
b00000000000000000000000100110011 #
1;
#615
0;
#616
b00000000000000000000000100110100 #
1;
#617
0;
#618
b00000000000000000000000100110101 #
1;
#619
0;
#620
b00000000000000000000000100110110 #
1;
#621
0;
#622
b00000000000000000000000100110111 #
1;
#623
0;
#624
b00000000000000000000000100111000 #
1;
#625
0;
#626
b00000000000000000000000100111001 #
1;
#627
0;
#628
b00000000000000000000000100111010 #
1;
#629
0;
#630
b00000000000000000000000100111011 #
1;
#631
0;
#632
b00000000000000000000000100111100 #
1;
#633
0;
#634
b00000000000000000000000100111101 #
1;
#635
0;
#636
b00000000000000000000000100111110 #
1;
#637
0;
#638
b00000000000000000000000100111111 #
1;
#639
0;
#640
b00000000000000000000000101000000 #
1;
#641
0;
#642
b00000000000000000000000101000001 #
1;
#643
0;
#644
b00000000000000000000000101000010 #
1;
#645
0;
#646
b00000000000000000000000101000011 #
1;
#647
0;
#648
b00000000000000000000000101000100 #
1;
#649
0;
#650
b00000000000000000000000101000101 #
1;
#651
0;
#652
b00000000000000000000000101000110 #
1;
#653
0;
#654
b00000000000000000000000101000111 #
1;
#655
0;
#656
b00000000000000000000000101001000 #
1;
#657
0;
#658
b00000000000000000000000101001001 #
1;
#659
0;
#660
b00000000000000000000000101001010 #
1;
#661
0;
#662
b00000000000000000000000101001011 #
1;
#663
0;
#664
b00000000000000000000000101001100 #
1;
#665
0;
#666
b00000000000000000000000101001101 #
1;
#667
0;
#668
b00000000000000000000000101001110 #
1;
#669
0;
#670
b00000000000000000000000101001111 #
1;
#671
0;
#672
b00000000000000000000000101010000 #
1;
#673
0;
#674
b00000000000000000000000101010001 #
1;
#675
0;
#676
b00000000000000000000000101010010 #
1;
#677
0;
#678
b00000000000000000000000101010011 #
1;
#679
0;
#680
b00000000000000000000000101010100 #
1;
#681
0;
#682
b00000000000000000000000101010101 #
1;
#683
0;
#684
b00000000000000000000000101010110 #
1;
#685
0;
#686
b00000000000000000000000101010111 #
1;
#687
0;
#688
b00000000000000000000000101011000 #
1;
#689
0;
#690
b00000000000000000000000101011001 #
1;
#691
0;
#692
b00000000000000000000000101011010 #
1;
#693
0;
#694
b00000000000000000000000101011011 #
1;
#695
0;
#696
b00000000000000000000000101011100 #
1;
#697
0;
#698
b00000000000000000000000101011101 #
1;
#699
0;
#700
b00000000000000000000000101011110 #
1;
#701
0;
#702
b00000000000000000000000101011111 #
1;
#703
0;
#704
b00000000000000000000000101100000 #
1;
#705
0;
#706
b00000000000000000000000101100001 #
1;
#707
0;
#708
b00000000000000000000000101100010 #
1;
#709
0;
#710
b00000000000000000000000101100011 #
1;
#711
0;
#712
b00000000000000000000000101100100 #
1;
#713
0;
#714
b00000000000000000000000101100101 #
1;
#715
0;
#716
b00000000000000000000000101100110 #
1;
#717
0;
#718
b00000000000000000000000101100111 #
1;
#719
0;
#720
b00000000000000000000000101101000 #
1;
#721
0;
#722
b00000000000000000000000101101001 #
1;
#723
0;
#724
b00000000000000000000000101101010 #
1;
#725
0;
#726
b00000000000000000000000101101011 #
1;
#727
0;
#728
b00000000000000000000000101101100 #
1;
#729
0;
#730
b00000000000000000000000101101101 #
1;
#731
0;
#732
b00000000000000000000000101101110 #
1;
#733
0;
#734
b00000000000000000000000101101111 #
1;
#735
0;
#736
b00000000000000000000000101110000 #
1;
#737
0;
#738
b00000000000000000000000101110001 #
1;
#739
0;
#740
b00000000000000000000000101110010 #
1;
#741
0;
#742
b00000000000000000000000101110011 #
1;
#743
0;
#744
b00000000000000000000000101110100 #
1;
#745
0;
#746
b00000000000000000000000101110101 #
1;
#747
0;
#748
b00000000000000000000000101110110 #
1;
#749
0;
#750
b00000000000000000000000101110111 #
1;
#751
0;
#752
b00000000000000000000000101111000 #
1;
#753
0;
#754
b00000000000000000000000101111001 #
1;
#755
0;
#756
b00000000000000000000000101111010 #
1;
#757
0;
#758
b00000000000000000000000101111011 #
1;
#759
0;
#760
b00000000000000000000000101111100 #
1;
#761
0;
#762
b00000000000000000000000101111101 #
1;
#763
0;
#764
b00000000000000000000000101111110 #
1;
#765
0;
#766
b00000000000000000000000101111111 #
1;
#767
0;
#768
b00000000000000000000000110000000 #
1;
#769
0;
#770
b00000000000000000000000110000001 #
1;
#771
0;
#772
b00000000000000000000000110000010 #
1;
#773
0;
#774
b00000000000000000000000110000011 #
1;
#775
0;
#776
b00000000000000000000000110000100 #
1;
#777
0;
#778
b00000000000000000000000110000101 #
1;
#779
0;
#780
b00000000000000000000000110000110 #
1;
#781
0;
#782
b00000000000000000000000110000111 #
1;
#783
0;
#784
b00000000000000000000000110001000 #
1;
#785
0;
#786
b00000000000000000000000110001001 #
1;
#787
0;
#788
b00000000000000000000000110001010 #
1;
#789
0;
#790
b00000000000000000000000110001011 #
1;
#791
0;
#792
b00000000000000000000000110001100 #
1;
#793
0;
#794
b00000000000000000000000110001101 #
1;
#795
0;
#796
b00000000000000000000000110001110 #
1;
#797
0;
#798
b00000000000000000000000110001111 #
1;
#799
0;
#800
b00000000000000000000000110010000 #
1;
#801
0;
#802
b00000000000000000000000110010001 #
1;
#803
0;
#804
b00000000000000000000000110010010 #
1;
#805
0;
#806
b00000000000000000000000110010011 #
1;
#807
0;
#808
b00000000000000000000000110010100 #
1;
#809
0;
#810
b00000000000000000000000110010101 #
1;
#811
0;
#812
b00000000000000000000000110010110 #
1;
#813
0;
#814
b00000000000000000000000110010111 #
1;
#815
0;
#816
b00000000000000000000000110011000 #
1;
#817
0;
#818
b00000000000000000000000110011001 #
1;
#819
0;
#820
b00000000000000000000000110011010 #
1;
#821
0;
#822
b00000000000000000000000110011011 #
1;
#823
0;
#824
b00000000000000000000000110011100 #
1;
#825
0;
#826
b00000000000000000000000110011101 #
1;
#827
0;
#828
b00000000000000000000000110011110 #
1;
#829
0;
#830
b00000000000000000000000110011111 #
1;
#831
0;
#832
b00000000000000000000000110100000 #
1;
#833
0;
#834
b00000000000000000000000110100001 #
1;
#835
0;
#836
b00000000000000000000000110100010 #
1;
#837
0;
#838
b00000000000000000000000110100011 #
1;
#839
0;
#840
b00000000000000000000000110100100 #
1;
#841
0;
#842
b00000000000000000000000110100101 #
1;
#843
0;
#844
b00000000000000000000000110100110 #
1;
#845
0;
#846
b00000000000000000000000110100111 #
1;
#847
0;
#848
b00000000000000000000000110101000 #
1;
#849
0;
#850
b00000000000000000000000110101001 #
1;
#851
0;
#852
b00000000000000000000000110101010 #
1;
#853
0;
#854
b00000000000000000000000110101011 #
1;
#855
0;
#856
b00000000000000000000000110101100 #
1;
#857
0;
#858
b00000000000000000000000110101101 #
1;
#859
0;
#860
b00000000000000000000000110101110 #
1;
#861
0;
#862
b00000000000000000000000110101111 #
1;
#863
0;
#864
b00000000000000000000000110110000 #
1;
#865
0;
#866
b00000000000000000000000110110001 #
1;
#867
0;
#868
b00000000000000000000000110110010 #
1;
#869
0;
#870
b00000000000000000000000110110011 #
1;
#871
0;
#872
b00000000000000000000000110110100 #
1;
#873
0;
#874
b00000000000000000000000110110101 #
1;
#875
0;
#876
b00000000000000000000000110110110 #
1;
#877
0;
#878
b00000000000000000000000110110111 #
1;
#879
0;
#880
b00000000000000000000000110111000 #
1;
#881
0;
#882
b00000000000000000000000110111001 #
1;
#883
0;
#884
b00000000000000000000000110111010 #
1;
#885
0;
#886
b00000000000000000000000110111011 #
1;
#887
0;
#888
b00000000000000000000000110111100 #
1;
#889
0;
#890
b00000000000000000000000110111101 #
1;
#891
0;
#892
b00000000000000000000000110111110 #
1;
#893
0;
#894
b00000000000000000000000110111111 #
1;
#895
0;
#896
b00000000000000000000000111000000 #
1;
#897
0;
#898
b00000000000000000000000111000001 #
1;
#899
0;
#900
b00000000000000000000000111000010 #
1;
#901
0;
#902
b00000000000000000000000111000011 #
1;
#903
0;
#904
b00000000000000000000000111000100 #
1;
#905
0;
#906
b00000000000000000000000111000101 #
1;
#907
0;
#908
b00000000000000000000000111000110 #
1;
#909
0;
#910
b00000000000000000000000111000111 #
1;
#911
0;
#912
b00000000000000000000000111001000 #
1;
#913
0;
#914
b00000000000000000000000111001001 #
1;
#915
0;
#916
b00000000000000000000000111001010 #
1;
#917
0;
#918
b00000000000000000000000111001011 #
1;
#919
0;
#920
b00000000000000000000000111001100 #
1;
#921
0;
#922
b00000000000000000000000111001101 #
1;
#923
0;
#924
b00000000000000000000000111001110 #
1;
#925
0;
#926
b00000000000000000000000111001111 #
1;
#927
0;
#928
b00000000000000000000000111010000 #
1;
#929
0;
#930
b00000000000000000000000111010001 #
1;
#931
0;
#932
b00000000000000000000000111010010 #
1;
#933
0;
#934
b00000000000000000000000111010011 #
1;
#935
0;
#936
b00000000000000000000000111010100 #
1;
#937
0;
#938
b00000000000000000000000111010101 #
1;
#939
0;
#940
b00000000000000000000000111010110 #
1;
#941
0;
#942
b00000000000000000000000111010111 #
1;
#943
0;
#944
b00000000000000000000000111011000 #
1;
#945
0;
#946
b00000000000000000000000111011001 #
1;
#947
0;
#948
b00000000000000000000000111011010 #
1;
#949
0;
#950
b00000000000000000000000111011011 #
1;
#951
0;
#952
b00000000000000000000000111011100 #
1;
#953
0;
#954
b00000000000000000000000111011101 #
1;
#955
0;
#956
b00000000000000000000000111011110 #
1;
#957
0;
#958
b00000000000000000000000111011111 #
1;
#959
0;
#960
b00000000000000000000000111100000 #
1;
#961
0;
#962
b00000000000000000000000111100001 #
1;
#963
0;
#964
b00000000000000000000000111100010 #
1;
#965
0;
#966
b00000000000000000000000111100011 #
1;
#967
0;
#968
b00000000000000000000000111100100 #
1;
#969
0;
#970
b00000000000000000000000111100101 #
1;
#971
0;
#972
b00000000000000000000000111100110 #
1;
#973
0;
#974
b00000000000000000000000111100111 #
1;
#975
0;
#976
b00000000000000000000000111101000 #
1;
#977
0;
#978
b00000000000000000000000111101001 #
1;
#979
0;
#980
b00000000000000000000000111101010 #
1;
#981
0;
#982
b00000000000000000000000111101011 #
1;
#983
0;
#984
b00000000000000000000000111101100 #
1;
#985
0;
#986
b00000000000000000000000111101101 #
1;
#987
0;
#988
b00000000000000000000000111101110 #
1;
#989
0;
#990
b00000000000000000000000111101111 #
1;
#991
0;
#992
b00000000000000000000000111110000 #
1;
#993
0;
#994
b00000000000000000000000111110001 #
1;
#995
0;
#996
b00000000000000000000000111110010 #
1;
#997
0;
#998
b00000000000000000000000111110011 #
1;
