lvl3/lab3/prelab.sv
module prelab (
    input clk, 
    input reset, // Asynchronous reset
    output reg [2:0] light // Traffic light output : 3'b001 (RED), 3'b010 (GREEN), 3'b100 (YELLOW)
);

    parameter RED = 2'b00;
    parameter GREEN = 2'b01;
    parameter YELLOW = 2'b10;
    parameter CLOCK_FREQ = 50;
    parameter DURATION = 5;
/* verilator lint_off UNOPTFLAT */
    reg [31:0] counter; // Adjusted to 32 bits
    reg [1:0] current_state, next_state;

    // Model state register (sequential logic)
    always @(posedge clk or posedge reset) begin
        if (reset) begin
            current_state <= RED;
            /* verilator lint_off BLKSEQ */
            counter =  0;
        end else begin
            current_state <= next_state;
            counter =  counter + 1;
        end
    end

    // Model next state decode logic (combinational logic)
    always @(*) begin
        case (current_state)
            RED: begin
                if (counter == CLOCK_FREQ * DURATION * 10) begin
                    next_state = GREEN;
                    counter =  0; // Reset counter
                end else begin
                    next_state = RED;
                end
            end
            GREEN: begin
                if (counter == CLOCK_FREQ * DURATION * 10) begin
                    next_state = YELLOW;
                    counter =  0; // Reset counter
                end else begin
                    next_state = GREEN;
                end
            end
            YELLOW: begin
                if (counter == CLOCK_FREQ * DURATION) begin
                    next_state = RED;
                    counter =  0; // Reset counter
                end else begin
                    next_state = YELLOW;
                end
            end
            default: begin
                next_state = RED;
                counter =  0; // Reset counter
            end
        endcase
    end

    // Model output logic (combinational logic)
    always @(*) begin
        case (current_state)
            RED: begin
                light = 3'b001; // RED light
            end
            GREEN: begin
                light = 3'b010; // GREEN light
            end
            YELLOW: begin
                light = 3'b100; // YELLOW light
            end
            default: begin
                light = 3'b001; // default to RED light
            end
        endcase
    end

endmodule

lvl_3/lab3/waveform.vcd
$version Generated by VerilatedVcd $end
$date Wed Jun 19 13:47:43 2024
 $end
$timescale   1ns $end

 $scope module TOP $end
  $var wire  1 ; clk $end
  $var wire  3 K light [2:0] $end
  $var wire  1 C reset $end
  $scope module prelab $end
   $var wire 32 k CLOCK_FREQ [31:0] $end
   $var wire 32 s DURATION [31:0] $end
   $var wire  2 [ GREEN [1:0] $end
   $var wire  2 S RED [1:0] $end
   $var wire  2 c YELLOW [1:0] $end
   $var wire  1 ; clk $end
   $var wire 32 # counter [31:0] $end
   $var wire  2 3 current_state [1:0] $end
   $var wire  3 K light [2:0] $end
   $var wire  2 + next_state [1:0] $end
   $var wire  1 C reset $end
  $upscope $end
 $upscope $end
$enddefinitions $end


#0
b00000000000000000000000000000000 #
b00 +
b11 3
1;
1C
b001 K
b00 S
b01 [
b10 c
b00000000000000000000000000110010 k
b00000000000000000000000000000101 s
#1
0;
#2
b00000000000000000000000000000001 #
b00 3
1;
0C
#3
0;
#4
b00000000000000000000000000000010 #
1;
#5
0;
#6
b00000000000000000000000000000011 #
1;
#7
0;
#8
b00000000000000000000000000000100 #
1;
#9
0;
#10
b00000000000000000000000000000101 #
1;
#11
0;
#12
b00000000000000000000000000000110 #
1;
#13
0;
#14
b00000000000000000000000000000111 #
1;
#15
0;
#16
b00000000000000000000000000001000 #
1;
#17
0;
#18
b00000000000000000000000000001001 #
1;
#19
0;
#20
b00000000000000000000000000001010 #
1;
#21
0;
#22
b00000000000000000000000000001011 #
1;
#23
0;
#24
b00000000000000000000000000001100 #
1;
#25
0;
#26
b00000000000000000000000000001101 #
1;
#27
0;
#28
b00000000000000000000000000001110 #
1;
#29
0;
#30
b00000000000000000000000000001111 #
1;
#31
0;
#32
b00000000000000000000000000010000 #
1;
#33
0;
#34
b00000000000000000000000000010001 #
1;
#35
0;
#36
b00000000000000000000000000010010 #
1;
#37
0;
#38
b00000000000000000000000000010011 #
1;
#39
0;
#40
b00000000000000000000000000010100 #
1;
#41
0;
#42
b00000000000000000000000000010101 #
1;
#43
0;
#44
b00000000000000000000000000010110 #
1;
#45
0;
#46
b00000000000000000000000000010111 #
1;
#47
0;
#48
b00000000000000000000000000011000 #
1;
#49
0;
#50
b00000000000000000000000000011001 #
1;
#51
0;
#52
b00000000000000000000000000011010 #
1;
#53
0;
#54
b00000000000000000000000000011011 #
1;
#55
0;
#56
b00000000000000000000000000011100 #
1;
#57
0;
#58
b00000000000000000000000000011101 #
1;
#59
0;
#60
b00000000000000000000000000011110 #
1;
#61
0;
#62
b00000000000000000000000000011111 #
1;
#63
0;
#64
b00000000000000000000000000100000 #
1;
#65
0;
#66
b00000000000000000000000000100001 #
1;
#67
0;
#68
b00000000000000000000000000100010 #
1;
#69
0;
#70
b00000000000000000000000000100011 #
1;
#71
0;
#72
b00000000000000000000000000100100 #
1;
#73
0;
#74
b00000000000000000000000000100101 #
1;
#75
0;
#76
b00000000000000000000000000100110 #
1;
#77
0;
#78
b00000000000000000000000000100111 #
1;
#79
0;
#80
b00000000000000000000000000101000 #
1;
#81
0;
#82
b00000000000000000000000000101001 #
1;
#83
0;
#84
b00000000000000000000000000101010 #
1;
#85
0;
#86
b00000000000000000000000000101011 #
1;
#87
0;
#88
b00000000000000000000000000101100 #
1;
#89
0;
#90
b00000000000000000000000000101101 #
1;
#91
0;
#92
b00000000000000000000000000101110 #
1;
#93
0;
#94
b00000000000000000000000000101111 #
1;
#95
0;
#96
b00000000000000000000000000110000 #
1;
#97
0;
#98
b00000000000000000000000000110001 #
1;
